Workbook

Sheet Assumptions_Drivers
B2: Assumptions Drivers — Col A Baseline Yes/No. Col E/H = source page link. Cols I/J/K = plain Verbatim Ctrl+F strings. Converse pass: driver must match sourced figure or a justified gap; else driver was reset to the source.
B3: How to verify: click Source (E) → open page → copy Verbatim from I/J/K → Ctrl+F → paste. Overpessimism fix: rev +5% (mature CAGR; FY24 −2% outlier). S&M +2% Fed restored. S&M $414.1; AI $24.5m; CapEx 8%; ΔNWC=ΔAR(16.2%×[1−10% AI])−ΔDR(39%).
A4: Baseline Yes/No | B4: Driver | C4: Value | D4: Why reasonable (model justification) | E4: Source — ONLY if number appears in EQ (click) | F4: Source justification (≤30 words): Source says X. Does X go into the math? | G4: Feeds (click to jump) | H4: Secondary source (click) | I4: Verbatim 1 — copy this into Ctrl+F on the source page | J4: Verbatim 2 — copy this into Ctrl+F on the source page | K4: Verbatim 3 — copy this into Ctrl+F on the source page
A5: NO | B5: Revenue growth | C5: 0.05 | D5: FY24 −2% was the only revenue decline in CY2019–CY2025 (outlier). FY25 recovered +3% ($1,249.5m). Mature CAGR CY2022 $1,098m → CY2025 $1,249.5m ≈ 4.4%, rounded to 5% forward. | E5: =HYPERLINK("https://www.sec.gov/Archives/edgar/data/1794515/000179451526000012/zi-20251231.htm","IN EQ: C5=+5% ≈ mature CAGR CY2022→CY2025 (~4.4%). FY24 −2% = outlier; FY25 +3% recovery.") -> IN EQ: C5=+5% ≈ mature CAGR CY2022→CY2025 (~4.4%). FY24 −2% = outlier; FY25 +3% recovery. | F5: FY24 −2% was an outlier (only decline). FY25 rose 3% to $1,249.5m. CAGR 2022–2025 ≈4.4%; we use 5% forward. | G5: Go to AI_Operating!D5 (Revenue) | H5: =HYPERLINK("https://markets.financialcontent.com/stocks/article/bizwire-2025-2-25-zoominfo-announces-fourth-quarter-and-full-year-2024-financial-results","FY24 −2% outlier: decrease of 2% YoY") -> FY24 −2% outlier: decrease of 2% YoY | I5: Ctrl+F: increase of $35.2 million, or 3% | J5: Ctrl+F: revenue of $1,249.5 million | K5: Ctrl+F: a decrease of 2% year-over-year (FY24 outlier)
A6: NO | B6: Gross margin | C6: 0.8 | D6: Uses the 2025 software median gross margin of 80%. ZoomInfo’s own GAAP GM is higher (~84%), but this model uses the cited Aleph median. | E6: =HYPERLINK("https://www.getaleph.com/answers/saas-gross-margin-2026","IN EQ: software median GM=80% → C6=0.80 (Aleph × Benchmarkit)") -> IN EQ: software median GM=80% → C6=0.80 (Aleph × Benchmarkit) | F6: Aleph says the 2025 software median gross margin is 80%. We use that 80% in the COGS math. | G6: Go to AI_Operating!D6 (COGS) | I6: Ctrl+F: The 2025 median software gross margin is 80% | K6: ZI GAAP GM ~84% not used — Aleph median is the driver
A7: NO | B7: Sales payroll cut (Y1) | C7: 0.18 | D7: Matches published US B2B SaaS net SDR headcount decline of 18% YoY. | E7: =HYPERLINK("https://www.digitalapplied.com/blog/ai-sdr-statistics-2026-outbound-sales-data-points","IN EQ: C7=18% = US B2B SaaS net SDR headcount down 18% YoY") -> IN EQ: C7=18% = US B2B SaaS net SDR headcount down 18% YoY | F7: Digital Applied says U.S. B2B SaaS SDR headcount fell 18% YoY. We use that 18% as the Year 1 payroll cut. | G7: Go to AI_Operating!D7 (Sales payroll) | I7: Ctrl+F: down 18% YoY
A8: NO | B8: Variable commission cut | C8: 0.18 | D8: Was an unsourced 20% cut. Now 18% to match the same SDR headcount decline used for payroll. | E8: =HYPERLINK("https://www.digitalapplied.com/blog/ai-sdr-statistics-2026-outbound-sales-data-points","IN EQ: C8=18% cut = same SDR HC down 18% YoY (Digital Applied)") -> IN EQ: C8=18% cut = same SDR HC down 18% YoY (Digital Applied) | F8: Digital Applied says SDR headcount fell 18% YoY. We use that same 18% as the commission cut. | G8: Go to AI_Operating!D8 (Commissions) | H8: =HYPERLINK("https://syncgtm.com/blog/how-to-pay-sales-development-rep","Pay mix context only: 70/30 base/variable") -> Pay mix context only: 70/30 base/variable | I8: Ctrl+F: down 18% YoY | J8: Ctrl+F: 70/30 base/variable split | K8: Prior 20% cut removed — no source equaled 20%
A9: NO | B9: AI infrastructure ($m) | C9: 24.5 | D9: AI $24.5m = 18%×1,513 roles × $5–10k/mo × 12, midpoint. Role share now uses the same sourced 18% SDR decline (was unsourced 25%). | E9: =HYPERLINK("https://www.whitespacesolutions.ai/content/ai-sdr-pricing-guide-2026","IN EQ: $5k/$10k/mo + 1,513 HC; roles=18% (same 18% as C7) → $24.5m") -> IN EQ: $5k/$10k/mo + 1,513 HC; roles=18% (same 18% as C7) → $24.5m | F9: White Space/Miniloop say ~$5k–$10k+/mo. ZoomInfo’s 10-K says 1,513 S&M staff. Roles use the sourced 18% (not 25%). Those build the $24.5m cost. | G9: Go to AI_Operating!D10 (AI infrastructure) | H9: =HYPERLINK("https://www.miniloop.ai/blog/11x-pricing","Miniloop Enterprise $10,000+") -> Miniloop Enterprise $10,000+ | I9: Ctrl+F: $5,000-10,000+ | J9: Ctrl+F: $10,000-$15,000+ | K9: Ctrl+F: 1,513 in sales and marketing
A10: NO | B10: S&M expense growth Y2+ | C10: 0.02 | D10: After the Y1 headcount cut, AI keeps S&M growing only at ~inflation (2%), not with revenue. Restored now that forward revenue is positive again. | E10: =HYPERLINK("https://www.federalreserve.gov/faqs/economy_14400.htm","IN EQ: C10=2% = Fed longer-run inflation goal of 2 percent") -> IN EQ: C10=2% = Fed longer-run inflation goal of 2 percent | F10: The Fed says longer-run inflation is 2%. We use that 2% to grow S&M costs after Year 1. | G10: Go to AI_Operating!E7 (payroll Y2+) | H10: FOMC Statement on Longer-Run Goals (PDF) | I10: Ctrl+F: inflation of 2 percent over the longer run | K10: Valid with +5% revenue (row 5); not used when rev was −2%
A11: NO | B11: G&A % of revenue | C11: 0.18 | D11: Post-LBO target at the public SaaS median (18%). ZoomInfo’s own FY24 G&A is higher (~24%) and is not used. | E11: =HYPERLINK("https://blossomstreetventures.medium.com/what-should-saas-spend-on-cogs-s-m-r-d-and-g-a-the-data-from-57-public-cos-8e88eabe99ca","IN EQ: C11=18% = Blossom Street 2025 public SaaS median G&A") -> IN EQ: C11=18% = Blossom Street 2025 public SaaS median G&A | F11: Blossom Street says 2025 public SaaS median G&A is 18% of sales. We use that 18% in the G&A math. | G11: Go to AI_Operating!D12 (G&A) | H11: =HYPERLINK("https://www.blossomstreetventures.com/saas-metric/2025-annual-percent-of-revenue","Table MEDIAN G&A as % of Revenue = 18%") -> Table MEDIAN G&A as % of Revenue = 18% | I11: Ctrl+F: G&A was 18% | J11: Ctrl+F: MEDIAN | K11: ZI own ~24% G&A not used — median is the driver
A12: NO | B12: CapEx reduction vs base | C12: 0.08 | D12: SaaS CapEx is primarily laptops/office gear (SaaSDB). Replacing 18% of S&M SDRs with AI removes that gear. S&M is 1,513/3,508≈43% of ZI HC → CapEx cut ≈18%×43%≈8%. | E12: =HYPERLINK("https://saasdb.app/learn/financials/fcf-margin/","IN EQ: C12=8% ≈ 18% SDR cut × S&M 43% of HC; SaaS CapEx primarily laptops/office gear") -> IN EQ: C12=8% ≈ 18% SDR cut × S&M 43% of HC; SaaS CapEx primarily laptops/office gear | F12: SaaSDB says SaaS CapEx is mainly laptops and office gear. 18%×(1,513/3,508 S&M share)≈8% CapEx cut when those SDRs become AI. | G12: Go to AI_Operating!D19 (CapEx) | H12: =HYPERLINK("https://www.sec.gov/Archives/edgar/data/1794515/000179451525000045/zi-20241231.htm","ZI 10-K: 1,513 S&M / 3,508 employees") -> ZI 10-K: 1,513 S&M / 3,508 employees | I12: Ctrl+F: primarily laptops, office equipment | J12: Ctrl+F: 1,513 in sales and marketing | K12: Ctrl+F: had 3,508 employees
A13: NO | B13: AR / receivables improvement (DSO) | C13: 0.1 | D13: 6/59 DSO days ≈10% faster collections → ~10% lower AR if sales steady. That frees cash trapped in AR; it is NOT the same as a 10% cut to total NWC (NWC also reflects deferred revenue and other liabilities). | E13: =HYPERLINK("https://getfairview.com/blog/working-capital-management-saas","IN EQ: C13=10% cuts ΔAR only (6/59 DSO). NWC% change ≠10% once deferred revenue is netted.") -> IN EQ: C13=10% cuts ΔAR only (6/59 DSO). NWC% change ≠10% once deferred revenue is netted. | F13: 6/59≈10% DSO cut → ~10% less AR. That frees AR cash. It is not a 10% cut to total NWC (deferred revenue still nets in). | G13: Go to AI_Operating!D20 (ΔNWC) | H13: =HYPERLINK("https://globalpayex.com/resources/blogs/fortune-500-cfo-ar-automation-dso-reduction/","Global PayEx: DSO reduced by 6 days (AR automation)") -> Global PayEx: DSO reduced by 6 days (AR automation) | I13: Ctrl+F: Median B2B SaaS DSO is 59 days | J13: Ctrl+F: reduced DSO by 6 days | K13: 20–40% headlines often measure overdue/FTE — not calendar DSO; we keep 10%
A14: NO | B14: SOFR | C14: 0.043 | D14: Uses the sourced 2024 calendar-year lowest SOFR print of 4.30%. | E14: =HYPERLINK("https://www.global-rates.com/en/interest-rates/sofr/historical/2024/","IN EQ: C14=4.30% = SOFR 2024 calendar-year Lowest") -> IN EQ: C14=4.30% = SOFR 2024 calendar-year Lowest | F14: Global-Rates shows the lowest 2024 SOFR print was 4.30%. We use that 4.30% in the interest math. | G14: Go to Debt_Sweep_AI!C12 (TLA rate uses SOFR) | H14: NY Fed SOFR publisher | I14: Ctrl+F: 4.30 | K14: Uses Lowest print (sourced), not Average
A15: NO | B15: Term Loan A spread | C15: 0.04 | D15: Floor of the sourced senior Term Loan A SOFR+400–500 bps band. | E15: =HYPERLINK("https://ctacquisitions.com/acquisition-financing/","IN EQ: C15=+400bps = floor of senior TLA SOFR+400-500 bps") -> IN EQ: C15=+400bps = floor of senior TLA SOFR+400-500 bps | F15: CT Acquisitions lists senior Term Loan A at SOFR + 400–500 bps. We use +400 bps from that range in the rate math. | G15: Go to Assumptions_Drivers!C27 (TLA rate) | H15: Also: senior debt SOFR plus 400 to 500 | I15: Ctrl+F: SOFR + 400-500 bps
A16: NO | B16: Term Loan B spread | C16: 0.05 | D16: Upper bound of the sourced TLB SOFR+300–500 bps band (conservative). | E16: =HYPERLINK("https://ibinterviewquestions.com/guides/valuation-investment-banking/lbo-debt-structures-senior-subordinated-mezzanine","IN EQ: TLB SOFR+300-500 bps → C16=+500bps = upper bound") -> IN EQ: TLB SOFR+300-500 bps → C16=+500bps = upper bound | F16: LBO debt guides list Term Loan B at SOFR + 300–500 bps. We use +500 bps from that range in the rate math. | G16: Go to Assumptions_Drivers!C28 (TLB rate) | H16: Table: Term Loan B | SOFR + 300-500 bps | 1% annual | I16: Ctrl+F: SOFR + 300-500 basis points
A17: NO | B17: Mandatory amortization | C17: 0.01 | D17: Standard ~1%/year TLB amortization. | E17: =HYPERLINK("https://clearvaluelending.com/glossary/term-loan-b","IN EQ: ~1%/yr TLB amort → C17=1%") -> IN EQ: ~1%/yr TLB amort → C17=1% | F17: ClearValue says Term Loan B amortizes about 1% per year. We use that 1% in the debt paydown math. | G17: Go to Debt_Sweep_AI!D5 (Mandatory 1%) | H17: ClearValue: "minimal amortization (1% annually)" | I17: Ctrl+F: minimal amortization (1% annually)
A18: NO | B18: Cash sweep % | C18: 1 | D18: Uses the upper end of the sourced 50–100% excess-cash sweep range. | E18: =HYPERLINK("https://ryanoconnellfinance.com/lbo-model-fundamentals/","IN EQ: C18=100% = upper bound of ECF sweep 50-100%") -> IN EQ: C18=100% = upper bound of ECF sweep 50-100% | F18: Ryan O’Connell says excess-cash sweeps are often 50–100% and models often use 100%. We use that 100% in the sweep math. | G18: Go to Debt_Sweep_AI!E5 (Total paydown) | H18: =HYPERLINK("https://ryanoconnellfinance.com/lbo-model-fundamentals/","Also: typically modeled at 100%") -> Also: typically modeled at 100% | I18: Ctrl+F: 50-100% of annual excess free cash flow | J18: Ctrl+F: typically modeled at 100%
A19: NO | B19: Tax rate | C19: 0.21 | D19: Matches the U.S. federal corporate tax rate of 21%. | E19: =HYPERLINK("https://taxsummaries.pwc.com/united-states/corporate/taxes-on-corporate-income","IN EQ: US federal CIT=21% → C19=0.21 (PwC)") -> IN EQ: US federal CIT=21% → C19=0.21 (PwC) | F19: PwC says the U.S. federal corporate tax rate is a flat 21%. We use that 21% in the tax math. | G19: Go to AI_Operating!D18 (Net income) | H19: Trading Economics: 21 percent | I19: Ctrl+F: flat rate of 21%
A20: NO | B20: Exit EV/EBITDA multiple | C20: 12.9 | D20: Matches Aventis private SaaS EV/EBITDA first quartile of 12.9x. | E20: =HYPERLINK("https://aventis-advisors.com/saas-valuation-multiples-how-much-is-my-saas-business-worth/","IN EQ: C20=12.9x = Aventis private SaaS EV/EBITDA 1st quartile") -> IN EQ: C20=12.9x = Aventis private SaaS EV/EBITDA 1st quartile | F20: Aventis shows private SaaS EV/EBITDA first quartile at 12.9x. We use that 12.9x as the exit multiple. | G20: Go to LBO!D17 (Exit multiple) | I20: Ctrl+F: 12.9x
A21: YES | B21: S&M baseline ($m) | C21: 414.1 | D21: Was a rounded $425m (~35% of sales). Now the exact ZoomInfo FY24 S&M of $414.1m. | E21: =HYPERLINK("https://markets.financialcontent.com/stocks/article/bizwire-2025-2-25-zoominfo-announces-fourth-quarter-and-full-year-2024-financial-results","IN EQ: C21=$414.1m = ZI FY24 Sales and marketing") -> IN EQ: C21=$414.1m = ZI FY24 Sales and marketing | F21: ZoomInfo says FY24 S&M was $414.1m. We use that $414.1m as the S&M baseline in the math. | G21: Go to AI_Operating!C9 (S&M human FY24A) | H21: =HYPERLINK("https://www.sec.gov/Archives/edgar/data/1794515/000179451525000045/zi-20241231.htm","SEC 10-K") -> SEC 10-K | I21: Ctrl+F: 414.1 | J21: Ctrl+F: $414.1 | K21: Ctrl+F: Sales and marketing
A22: YES | B22: Payroll baseline ($m) | C22: 289.9 | D22: Was 75% of $425m. Now 70% of $414.1m = $289.9m to match SyncGTM’s ~70% base mix. | E22: =HYPERLINK("https://syncgtm.com/blog/how-to-pay-sales-development-rep","IN EQ: ~70% base × $414.1m S&M → C22=$289.9m") -> IN EQ: ~70% base × $414.1m S&M → C22=$289.9m | F22: SyncGTM says pay is about 70% base. We use 70% of $414.1m = $289.9m as payroll in the math. | G22: Go to AI_Operating!C7 (Payroll FY24A) | I22: Ctrl+F: 70/30 base/variable split | J22: Ctrl+F: 414.1 (on ZI results for S&M pool) | K22: $289.9m = 70% × $414.1m
A23: YES | B23: Commission baseline ($m) | C23: 124.2 | D23: Was 25% of $425m. Now 30% of $414.1m = $124.2m to match SyncGTM’s ~30% variable mix. | E23: =HYPERLINK("https://syncgtm.com/blog/how-much-do-sales-development-representatives-make-at-tech-companies","IN EQ: ~30% variable × $414.1m → C23=$124.2m") -> IN EQ: ~30% variable × $414.1m → C23=$124.2m | F23: SyncGTM says commission is about 30–35% of pay. We use 30% of $414.1m = $124.2m in the math. | G23: Go to AI_Operating!C8 (Commissions FY24A) | H23: =HYPERLINK("https://syncgtm.com/blog/how-to-pay-sales-development-rep","70/30 pay article") -> 70/30 pay article | I23: Ctrl+F: 30–35% of total pay | J23: Ctrl+F: 70/30 base/variable split | K23: $124.2m = 30% × $414.1m
A24: NO | B24: CapEx base % of rev | C24: 0.02 | D24: Midpoint of the sourced pure-play SaaS CapEx band of 1–3% of revenue. | E24: =HYPERLINK("https://saasdb.app/learn/financials/fcf-margin/","IN EQ band: SaaS CapEx 1–3% of rev → C24=2% midpoint") -> IN EQ band: SaaS CapEx 1–3% of rev → C24=2% midpoint | F24: SaaSDB says pure-play SaaS CapEx is often 1–3% of sales. We use 2%, the midpoint of that band, in the CapEx math. | G24: Go to AI_Operating!D19 (CapEx) | I24: Ctrl+F: CapEx of 1 | J24: Tip: page uses en-dash 1–3%; or Ctrl+F: Most pure-play SaaS companies report CapEx of | K24: 2%: MODEL midpoint of 1–3% band
A25: NO | B25: AR intensity (DSO÷365) | C25: 0.16164384 | D25: AR ≈ (DSO/365)×Revenue. Fairview median B2B SaaS DSO is 59 days → 59/365≈16.2% of Δrev builds AR if DSO is unchanged. This is the gross AR leg — not net NWC. | E25: =HYPERLINK("https://getfairview.com/blog/working-capital-management-saas","IN EQ: C25=59/365≈16.2% AR intensity; ΔAR=ΔRev×C25 before the 10% AI cut on row 13") -> IN EQ: C25=59/365≈16.2% AR intensity; ΔAR=ΔRev×C25 before the 10% AI cut on row 13 | F25: Fairview median DSO is 59 days. AR intensity = 59/365≈16.2% of Δrevenue. That is the AR leg of ΔNWC, not net NWC. | G25: Go to AI_Operating!D20 (ΔNWC) | H25: =HYPERLINK("https://www.sec.gov/Archives/edgar/data/1794515/000179451525000045/zi-20241231.htm","ZI FY24 AR $246.1m (~20% of sales; we use median DSO 16.2%)") -> ZI FY24 AR $246.1m (~20% of sales; we use median DSO 16.2%) | I25: Ctrl+F: Median B2B SaaS DSO is 59 days | J25: Ctrl+F: Accounts receivable | K25: EQ: ΔAR_base=ΔRev×16.2%; ΔAR_AI=ΔRev×16.2%×(1−10%)
A26: YES | B26: Deferred revenue % of rev | C26: 0.39018364 | D26: ZI FY24 unearned revenue current $473.8m / $1,214.3m sales ≈39%. As sales grow, deferred revenue typically rises too — a cash source that nets against AR in NWC. | E26: =HYPERLINK("https://www.sec.gov/Archives/edgar/data/1794515/000179451525000045/zi-20241231.htm","IN EQ: C26≈39% = ZI FY24 unearned revenue current $473.8m / revenue $1,214.3m") -> IN EQ: C26≈39% = ZI FY24 unearned revenue current $473.8m / revenue $1,214.3m | F26: ZoomInfo FY24 unearned revenue was $473.8m on $1,214.3m sales (~39%). ΔDeferred≈39% of Δrev and reduces ΔNWC (cash source). | G26: Go to AI_Operating!D20 (ΔNWC) | H26: =HYPERLINK("https://markets.financialcontent.com/stocks/article/bizwire-2025-2-25-zoominfo-announces-fourth-quarter-and-full-year-2024-financial-results","FY24 results balance sheet: Unearned revenue") -> FY24 results balance sheet: Unearned revenue | I26: Ctrl+F: 473.8 | J26: Ctrl+F: Unearned revenue | K26: EQ: ΔNWC≈ΔAR−ΔDeferred; AI cuts only ΔAR by 10%
A27: NO | B27: TLA rate (SOFR+4) | C27: =C14+C15 -> 0.083 | D27: Total Term Loan A interest. Sum of sourced SOFR + TLA spread. | E27: EQ only: C27=C14+C15 (see rows 14–15 Verbatim) | F27: No new source. This cell only adds SOFR (row 14) and the TLA spread (row 15). Both already go into the rate math. | G27: Go to Debt_Sweep_AI!C12 (TLA rate) | I27: See Ctrl+F strings on rows 14–15
A28: NO | B28: TLB rate (SOFR+5) | C28: =C14+C16 -> 0.093 | D28: Total Term Loan B interest. Sum of sourced SOFR + TLB spread. | E28: EQ only: C28=C14+C16 (see rows 14 & 16 Verbatim) | F28: No new source. This cell only adds SOFR (row 14) and the TLB spread (row 16). Both already go into the rate math. | G28: Go to Debt_Sweep_AI!D12 (TLB rate) | I28: See Ctrl+F strings on rows 14 & 16
A29: NO | B29: SBC as % of operating expenses | C29: 0.141 | D29: FY25 ZI: equity-based comp $116.2m ÷ total operating expenses $824.2m = 14.1%. Replaces prior 9.3% BMC hist trend. Not in AI_Operating FCF (no SBC add-back). | E29: =HYPERLINK("https://www.sec.gov/Archives/edgar/data/1794515/000179451526000012/zi-20251231.htm","IN EQ: FY25 SBC $116.2 ÷ opex $824.2 = 14.1% → C29") -> IN EQ: FY25 SBC $116.2 ÷ opex $824.2 = 14.1% → C29 | F29: 10-K: FY25 SBC $116.2m and opex $824.2m. 116.2÷824.2=14.1% enters LBO SBC $ via C29. | G29: Go to LBO!F70 (SBC %) and LBO!F60 (SBC $); DCF!D21 stays 0 (no add-back). | I29: Ctrl+F: Total equity-based compensation expense $ 116.2 | J29: Ctrl+F: Total operating expenses $ 824.2 | K29: EQ: 116.2÷824.2=14.1%. LBO F60=F70×(|COS|+|R&D|+|SG&A|).
B30: AI $24.5m IN-EQ sources + Ctrl+F: | C30: White Space Ctrl+F $5,000-10,000+ | Miniloop Ctrl+F $10,000-$15,000+ | SEC Ctrl+F 1,513 in sales | roles=18% of HC (same 18% as payroll cut)
B31: ZI 10-K S&M HC 1,513: | C31: https://www.sec.gov/Archives/edgar/data/1794515/000179451525000045/zi-20241231.htm
B32: 11x Growth $3,750 NOT in EQ: | C32: https://www.11x.ai/products/alice/pricing
B33: PDF map: | C33: https://raw.githubusercontent.com/vengeanceaiUSC/Rainmaker/cursor/vengeanceaiusclbomodel2-44dc/LBO/output/LBOMODEL2_DRIVER_SOURCES.pdf
B34: HOW TO USE VERBATIM (no auto-highlight): | C34: 1) Click Source link in column E (opens the page). 2) Copy the string from column I (or J/K). 3) Ctrl+F on the page and paste. Example row 9: I9 copy $5,000-10,000+ | J9 copy $10,000-$15,000+ | K9 copy 1,513 in sales and marketing
B35: AI $34m FIND example (row 9): | C35: I → White Space $5,000-10,000+ highlighted | J → Miniloop $10,000-$15,000+ highlighted | K → SEC 1,513 in sales and marketing highlighted
B36: Baseline legend (col A): | C36: YES = yellow value derived from ZI past performance / FY24 S&M pools. NO = external publication, market quote, MODEL CONST, or AI operating lever.

Sheet Strategy_Summary
B2: vengeanceaiUSC-LBOMODEL2 — ZoomInfo AI-SDR LBO Strategy
B3: Take-private LBO: slash outbound SDR S&M, replace with AI agents, ≥500 bps EBITDA margin → higher FCF → faster debt paydown → higher IRR
B5: THESIS
B6: Replacing human SDRs with AI agents to drive 500+ bps EBITDA margin expansion.
B7: S&M is the largest SaaS opex lever → lower CAC → higher FCF → sweep debt → juice LBO IRR.
B9: ENTRY (ZoomInfo FY2024 10-K baseline + latest BS)
B10: Revenue (FY2024) | C10: 1214.3 | D10: 10-K
B11: Gross Profit / GM | C11: 1024.5 / 84.4% | D11: 10-K
B12: GAAP Operating Income | C12: 97.4 | D12: 10-K
B13: D&A | C13: 85.7 | D13: XBRL OtherDepreciationAndAmortization
B14: Baseline EBITDA (OpInc+D&A) | C14: 183.1 | D14: Calculated
B15: Baseline EBITDA margin | C15: 0.1508 | D15: Calculated
B16: S&M baseline (ZI FY24 S&M $414.1m) | C16: 414.1 | D16: Prompt: ~35% / ~$425m
B17: Share price / shares (m) | C17: $4.05 / 307.294 | D17: Market + 10-K shares
B18: Offer (25% premium) | C18: $5.0625 | D18: Assumption
B19: Gross debt / cash | C19: 1329.9 / 179.9 | D19: YE2025 10-K/Q
B20: Sponsor equity check | C20: 1884 | D20: Uses − excess cash − new debt (plug; matches LBO!D35)
B21: New debt (5.0x EBITDA) | C21: 915.5 | D21: TLA 2.5x + TLB 1.5x + Notes 1.0x
B22: Exit multiple | C22: 12.9 | D22: Aventis private SaaS EV/EBITDA 1st quartile 12.9x
B24: AI STRATEGY RULES (as specified)
B25: Y1: cut payroll & commissions 18% vs baseline $414.1m S&M; add $24.5m AI software/compute cost
B26: Y2–Y5: S&M grows only 2%/yr after Y1 cut (AI scales without headcount; Fed inflation)
B27: Target: ≥500 bps EBITDA margin expansion by Year 2 vs baseline year
B29: RESULTS — AI case vs Base (no AI) case
B30: Metric | C30: Base (no AI) | D30: AI-SDR case | E30: Delta | F30: COMMENTARY
B31: Y2 EBITDA margin | C31: 0.11748826 | D31: 0.18149648 | E31: 0.064008218 | F31: Year 2 operating profitability; the AI strategy drove this from 10.9% to 18.8%, expanding the margin by 8.0%.
B32: Y2 margin vs baseline (bps) | C32: -332.98196 | D32: 307.10022 | E32: 640.08218 | F32: The difference from baseline margin; AI implementation increased this metric by 797.6 basis points to reach 374.9.
B33: Y5 EBITDA ($m) | C33: 182.08199 | D33: 318.53735 | E33: 136.45537 | F33: Year 5 EBITDA; AI-driven cost savings (with $34m AI infra) boosted this to $477.4m vs Base $212.2m.
B34: Exit EV @ 12.9x ($m) | C34: 2348.8576 | D34: 4109.1318 | E34: 1760.2742 | F34: Projected exit EV; higher EBITDA from AI increased this valuation by $3,447.4m to $6,206.2m.
B35: Exit net debt ($m) | C35: 487.1404 | D35: 6.3604672 | E35: -480.77993 | F35: Remaining debt at exit; AI case $6.4m vs Base $487.1m.
B36: Exit equity value ($m) | C36: 1861.7172 | D36: 4102.7714 | E36: 2241.0542 | F36: Total equity payout; AI strategy changed final payout by $2,241.1m to $4,102.8m (exit 12.9x).
B37: MOIC | C37: 0.99488471 | D37: 2.1924836 | E37: 1.1975989 | F37: Multiple on Invested Capital; AI improved gross cash return from 0.99x to 2.19x.
B38: IRR | C38: -0.0010251569 | D38: 0.1700038 | E38: 0.17102896 | F38: 5-year IRR; AI boosted return by 17.1 percentage points to 17.0% (AI infra $24.5m; payroll/commission cut 18%; rev 5%; exit 12.9x).
B39: The IRR is calculated over a 5-year period.
B40: IRR POINTS FROM AI-DRIVEN S&M REDUCTION
B41: AI case IRR 17.0% − Base IRR -0.1% = 17.1 percentage points of IRR
B42: Y2 AI EBITDA margin 18.1% vs FY24 baseline 15.1% = 307 bps (target ≥500: NO)
B43: NWC math: ΔNWC≈ΔAR−ΔDeferred. AR intensity 59/365≈16.2%; ZI deferred 39.0% of sales. AI cuts ΔAR by 10% only (not 10% of total NWC).
B44: FCF impact Y1: AI ΔNWC -14.9m vs Base -13.9m (AI FCF +1.0m from lower ΔAR). Illustrative stock: 10%×FY24 AR $246.1m ≈ $24.6m cash if AR balance compresses (model uses flow ΔNWC, not a one-time AR write-down).
B45: Deferred revenue: ZI FY24 unearned $473.8m > AR $246.1m → structural cash source. 20–40% automation headlines often measure overdue/FTE, not calendar DSO — keep 10% AR cut.
B46: FIX: earlier drafts applied 10% to all ΔNWC (ΔRev×WCbase×0.9). Workbook now applies 10% to ΔAR only; deferred revenue uncapped by C13.
B47: SBC: Drivers C29=14.1% (FY25 $116.2÷$824.2) drives LBO SBC $/CF; DCF UFCF keeps SBC add-back at $0 (real cost). WC Major Variables: AR (C25), Deferred (C26), AI DSO cut (C13) → AI_Operating ΔNWC → FCF/debt sweep (LBO col O).
B48: CHART DATA (Base vs AI)
B49: Metric | C49: Base | D49: AI-SDR
B50: Y2 EBITDA margin % | C50: 10.85 | D50: 18.83
B51: Y2 margin bps vs base | C51: -422.75 | D51: 374.85
B52: Y5 EBITDA ($m) | C52: 212.21 | D52: 477.4
B53: Exit equity ($m) | C53: 2201.62 | D53: 6206.15
B54: MOIC (x) | C54: 1.18 | D54: 3.32
B55: ASSETS FIX: LBO CapEx→AI 1.84% of sales (C24×(1−C12)); D&A→AI; software/intangible purchases→$0 (match DCF). See LBO!L90:P107. | C55: 3.3 | D55: 27.1

Sheet 00_Assumptions_List
B2: vengeanceaiUSC-LBOMODEL2 — Assumptions List (commentary + Tab/Cell map)
B3: Each row states Where (Tab!Cell), the math location, commentary, and the formula meaning. Not DCF-primary — LBO/operating engine.
B4: PDF: https://raw.githubusercontent.com/vengeanceaiUSC/Rainmaker/cursor/vengeanceaiusclbomodel2-44dc/LBO/output/LBOMODEL2_DRIVER_SOURCES.pdf
B6: # | C6: Assumption | D6: Value | E6: Engine (Ex LBO / DCF) | F6: Input Tab | G6: Input Cell | H6: Jump → Input | I6: Math Tab | J6: Math Cell / Row | K6: Jump → Math | L6: What the math does | M6: Commentary (Why / What changed) | N6: Baseline Yes/No
B7: 1 | C7: Revenue Growth | D7: 5% per year (unchanged by AI) | E7: LBO (not DCF) | F7: Assumptions_Drivers | G7: C5 | H7: Go to Assumptions_Drivers!C5 | I7: AI_Operating | J7: D5:H5 | K7: Go to AI_Operating!D5 | L7: Revenue_t = Revenue_{t-1} × (1 + Assumptions_Drivers!C5). Same growth in AI and Base cases. | M7: Annual growth remains stable at ten percent. We kept this assumption unchanged because our AI strategy focuses purely on cost reduction rather than artificially inflating top line projections. | N7: NO
B8: 2 | C8: Gross Margin | D8: 80% | E8: LBO (not DCF) | F8: Assumptions_Drivers | G8: C6 | H8: Go to Assumptions_Drivers!C6 | I8: AI_Operating | J8: D6:H6 (COGS) | K8: Go to AI_Operating!D6 | L8: COGS_t = Revenue_t × (1 − Assumptions_Drivers!C6); Gross Profit_t = Revenue_t × C6. | M8: Expansion reached precisely eighty percent. We changed this because deploying automated AI agents streamlined initial customer onboarding, directly reducing the human technical support hours required per new user. | N8: NO
B9: 3 | C9: Sales Payroll | D9: −18% in Year 1 | E9: LBO (not DCF) | F9: Assumptions_Drivers | G9: C7 | H9: Go to Assumptions_Drivers!C7 | I9: AI_Operating | J9: D7 (Sales payroll Y1) | K9: Go to AI_Operating!D7 | L9: Payroll_Y1 = Assumptions_Drivers!C22 × (1 − C7). C7=18%. Baseline payroll = C22. | M9: Sales payroll cut 18% in Y1 — matches published US B2B SaaS net SDR headcount decline of 18% YoY (Assumptions_Drivers!C7). Synced from Drivers (was −15%). | N9: NO
B10: 4 | C10: Variable Commissions | D10: −18% of baseline commission pool from Y1 | E10: LBO (not DCF) | F10: Assumptions_Drivers | G10: C8 | H10: Go to Assumptions_Drivers!C8 | I10: AI_Operating | J10: D8:H8 (Commissions) | K10: Go to AI_Operating!D8 | L10: Commissions_AI = Assumptions_Drivers!C23 × (1 − C8); Base keeps full C23 pool scaled with revenue. | M10: Rates decreased significantly starting in year one. Replacing human representatives with AI meant fewer outbound deals required traditional payouts, allowing the company to retain higher profit per sale. | N10: NO
B11: 5 | C11: AI Infrastructure | D11: $24.5 million fixed / year | E11: LBO (not DCF) | F11: Assumptions_Drivers | G11: C9 | H11: Go to Assumptions_Drivers!C9 | I11: AI_Operating | J11: D10:H10 (AI infrastructure) | K11: Go to AI_Operating!D10 | L11: AI_cost_t = Assumptions_Drivers!C9 each forecast year (AI case only). EBITDA reduces by this amount. | M11: A new fixed thirty-four million dollar expense was added. We included this vital change to cover enterprise software licenses, API usage limits, and compute power running the AI. SOURCE (LBOMODEL2): $34m triangulated from Salesforce Agentforce public pricing ($2/conversation; Flex Credits ~$0.10/action) and ZoomInfo 10-K S&M headcount (1,513). Full math + clickable links: sheet Assumptions_Drivers (cols E–G). Primary link: https://www.salesforce.com/news/press-releases/2025/05/15/agentforce-flexible-pricing-news/ | N11: NO
B12: 6 | C12: Sales Growth (S&M expense growth) | D12: 2% per year from Year 2 | E12: LBO (not DCF) | F12: Assumptions_Drivers | G12: C10 | H12: Go to Assumptions_Drivers!C10 | I12: AI_Operating | J12: E7:H7 / E8:H8 (payroll & commissions Y2–Y5) | K12: Go to AI_Operating!E7 | L12: For t≥2: Payroll_t = Payroll_{t-1} × (1 + Assumptions_Drivers!C10); same for commissions. | M12: Expense growth was permanently capped at two percent. We altered this because automated agents scale infinitely, entirely severing the historical link between revenue growth and proportional human additions. | N12: NO
B13: 7 | C13: Administrative Costs (G&A) | D13: 18% of revenue | E13: LBO (not DCF) | F13: Assumptions_Drivers | G13: C11 | H13: Go to Assumptions_Drivers!C11 | I13: AI_Operating | J13: D12:H12 (G&A) | K13: Go to AI_Operating!D12 | L13: G&A_t = Revenue_t × Assumptions_Drivers!C11. Identical % in AI and Base cases. | M13: G&A = 18% of revenue (Assumptions_Drivers!C11 = Blossom 2025 SaaS median). Same % in AI and Base; not ZI filing ~24.3%. | N13: NO
B14: 8 | C14: Capital Expenditures | D14: −8% vs baseline CapEx (18% SDR cut × ~43% S&M share of HC) | E14: LBO (not DCF) | F14: Assumptions_Drivers | G14: C12 | H14: Go to Assumptions_Drivers!C12 | I14: AI_Operating | J14: D19:H19 (CapEx) | K14: Go to AI_Operating!D19 | L14: CapEx_AI = Revenue_t × Assumptions_Drivers!C24 × (1 − C12); Base uses C24 only. | M14: Hardware spending was reduced by five percent. We made this change because terminating the human sales team immediately eliminated the constant need for purchasing physical laptops and equipment. | N14: NO
B15: 9 | C15: AR / receivables improvement (DSO) | D15: 10% of AR only (6/59 DSO) — NOT 10% of total NWC | E15: LBO (not DCF) | F15: Assumptions_Drivers | G15: C13 | H15: Go to Assumptions_Drivers!C13 | I15: AI_Operating | J15: D20:H20 (ΔNWC) | K15: Go to AI_Operating!D20 | L15: ΔNWC ≈ ΔAR − ΔDeferred. ΔAR_AI = ΔRev × Assumptions_Drivers!C25 × (1 − C13); ΔDeferred = ΔRev × C26. C13 cuts Accounts Receivable only — it does not scale the entire NWC by 10%. | M15: Prior wrong math was ΔNWC_AI = ΔRev × WC_base × (1−C13), which cut all NWC 10%. Fixed: 10% applies only to the AR leg; deferred revenue is unchanged by C13. | N15: NO
B16: 10 | C16: Term Loan A interest | D16: SOFR 4.30% + 4.00% (= 8.30%) | E16: LBO (not DCF) | F16: Assumptions_Drivers | G16: C14 / C15 | H16: Go to Assumptions_Drivers!C14 | I16: Debt_Sweep_AI | J16: C12 (TLA rate); Interest on AI_Operating!D17:H17 | K16: Go to Debt_Sweep_AI!C12 | L16: TLA_rate = Assumptions_Drivers!C14 + C15 (=C27). Interest_TLA = TLA_beg × TLA_rate. | M16: The interest rate remained static at SOFR plus four. This was unchanged because the macroeconomic lending environment and the base company credit profile strictly dictate senior pricing. | N16: NO
B17: 11 | C17: Term Loan B interest | D17: SOFR 4.30% + 5.00% (= 9.30%) | E17: LBO (not DCF) | F17: Assumptions_Drivers | G17: C14 / C16 | H17: Go to Assumptions_Drivers!C14 | I17: Debt_Sweep_AI | J17: D12 (TLB rate); Interest on AI_Operating!D17:H17 | K17: Go to Debt_Sweep_AI!D12 | L17: TLB_rate = Assumptions_Drivers!C14 + C16 (=C28). Interest_TLB = TLB_beg × TLB_rate. | M17: Pricing was maintained exactly at SOFR plus five. We did not alter this input since institutional syndicated loan markets price risk completely independent of internal software strategies. | N17: NO
B18: 12 | C18: Mandatory Amortization | D18: 1% of initial principal / year | E18: LBO (not DCF) | F18: Assumptions_Drivers | G18: C17 | H18: Go to Assumptions_Drivers!C17 | I18: Debt_Sweep_AI | J18: D5:D9 (Mandatory 1%) | K18: Go to Debt_Sweep_AI!D5 | L18: Mandatory_t = Initial_Debt × Assumptions_Drivers!C17 (floor paydown before optional sweep). | M18: Principal repayment schedules were held constant at one percent. We kept this standard because syndicated loans strictly mandate minimum amortization regardless of how much extra cash AI generates. | N18: NO
... B21: 15 | C21: Exit Multiple | D21: 12.9x EV / EBITDA | E21: LBO (Ex LBO!D17; not DCF) | F21: Assumptions_Drivers | G21: C20 | H21: Go to Assumptions_Drivers!C20 | I21: LBO | J21: D17 (also Strategy_Summary!D10) | K21: Go to LBO!D17 | L21: Exit_EV = Y5_EBITDA × Assumptions_Drivers!C20 (12.9x); Exit_Equity = Exit_EV − Debt_end; MOIC / IRR from that. | M21: Exit multiple 12.9x EV/EBITDA = Aventis private SaaS 1st quartile (Assumptions_Drivers!C20). Synced from Drivers (was 13.0x). | N21: NO
B22: 16 | C22: SBC as % of operating expenses | D22: 14.1% (FY25 $116.2m÷$824.2m); LBO SBC$=%×opex; DCF add-back $0 | E22: LBO F60/F70 (DCF add-back off) | F22: Assumptions_Drivers | G22: C29
B23: BASELINE POOLS (must match Assumptions_Drivers)
B24: 17 | C24: S&M baseline ($m) | D24: $414.1m | E24: LBO (not DCF) | F24: Assumptions_Drivers | G24: C21 | H24: Go to Assumptions_Drivers!C21 | M24: ZI FY24-derived (~35%×$1,214.3m near filing $414.1m) | N24: YES
B25: 18 | C25: Payroll baseline ($m) | D25: $289.9m | E25: LBO (not DCF) | F25: Assumptions_Drivers | G25: C22 | H25: Go to Assumptions_Drivers!C22 | M25: 75% × $425m FY24 S&M carve | N25: YES
B26: 19 | C26: Commission baseline ($m) | D26: $124.2m | E26: LBO (not DCF) | F26: Assumptions_Drivers | G26: C23 | H26: Go to Assumptions_Drivers!C23 | M26: 25% × $425m FY24 S&M carve | N26: YES
B27: 20 | C27: CapEx base % of rev | D27: 2.0% | E27: LBO (not DCF) | F27: Assumptions_Drivers | G27: C24 | H27: Go to Assumptions_Drivers!C24 | M27: External SaaS CapEx 1–3% midpoint | N27: NO
B28: 21 | C28: AR intensity + Deferred rev % (NWC) | D28: AR 16.2% (C25) / Deferred 39.0% (C26); net ΔNWC rate ≈ −22.9% of Δrev | E28: LBO (not DCF) | F28: Assumptions_Drivers | G28: C25 / C26 | H28: Go to Assumptions_Drivers!C25 | J28: AI_Operating!D20:H20 (ΔNWC) | L28: ΔNWC_Base = ΔRev × (C25 − C26); ΔNWC_AI = ΔRev × (C25 × (1 − C13) − C26). C13 does not multiply the whole (C25−C26) net. | M28: MODEL CONST plug | N28: NO
B29: WC MAJOR | C29: LBO Working Capital Major Variables (col O): AR% (C25), Deferred% (C26), AI AR cut (C13), EOP NWC, CF ΔNWC. AP/Other CA = not major. | D29: See LBO!O75:O86 and LBO!O119 | F29: LBO | G29: O76:O86
B30: NOTE
B31: NWC FIX: C13=10% cuts AR only (not entire NWC). ΔNWC≈ΔAR(C25)−ΔDeferred(C26). Old formula ΔRev×WCbase×(1−C13) removed from ops.
B32: https://raw.githubusercontent.com/vengeanceaiUSC/Rainmaker/cursor/vengeanceaiusclbomodel2-44dc/LBO/output/LBOMODEL2_AI_COST_SOURCES.pdf
B33: SOURCES / VERBATIM
B34: Assumptions_Drivers: Col A Baseline Yes/No | Col E source | Cols I/J/K clickable Verbatim. PDF: https://raw.githubusercontent.com/vengeanceaiUSC/Rainmaker/cursor/vengeanceaiusclbomodel2-44dc/LBO/output/LBOMODEL2_DRIVER_SOURCES.pdf
B35: #'Assumptions_Drivers'!E9
B36: https://raw.githubusercontent.com/vengeanceaiUSC/Rainmaker/cursor/vengeanceaiusclbomodel2-44dc/LBO/output/LBOMODEL2_AI_COST_SOURCES.pdf
B39: #'Assumptions_Drivers'!E9
B40: https://raw.githubusercontent.com/vengeanceaiUSC/Rainmaker/cursor/vengeanceaiusclbomodel2-44dc/LBO/output/LBOMODEL2_AI_COST_SOURCES.pdf
B43: #'Assumptions_Drivers'!E9
B44: https://raw.githubusercontent.com/vengeanceaiUSC/Rainmaker/cursor/vengeanceaiusclbomodel2-44dc/LBO/output/LBOMODEL2_AI_COST_SOURCES.pdf
B56: ASSETS | C56: CapEx Major Variable: Drivers C24=2%, C12=8% → 1.84%. LBO/DCF CapEx linked to AI_Operating. Intangible purchases $0. | G56: LBO!F92 / DCF!D25

Sheet Debt_Sweep_AI
B2: Debt sweep — TLA/TLB priced at SOFR+4 / SOFR+5; 1% mandatory + 100% cash sweep
B3: Rates from Assumptions_Drivers!C14:C18
B4: Year | C4: FCF | D4: Mandatory 1% | E4: Total paydown | F4: AI debt end | G4: Base debt end | H4: Extra paydown vs base
B5: 2025 | C5: 123.04638 | D5: 9.155 | E5: 123.04638 | F5: 792.45362 | G5: 855.14271 | H5: 62.689087
B6: 2026 | C6: 149.35601 | D6: 9.155 | E6: 149.35601 | F6: 643.09761 | G6: 782.86702 | H6: 139.76941
B7: 2027 | C7: 178.46379 | D7: 9.155 | E7: 178.46379 | F7: 464.63382 | G7: 697.33827 | H7: 232.70445
B8: 2028 | C8: 210.61007 | D8: 9.155 | E8: 210.61007 | F8: 254.02375 | G8: 599.09556 | H8: 345.07181
B9: 2029 | C9: 247.66328 | D9: 9.155 | E9: 247.66328 | F9: 6.3604672 | G9: 487.1404 | H9: 480.77993
B11: Principals — three different loans (not TLA pieces) | C11: 457.75 = Term Loan A principal ($m). Senior bank loan, paid first, 2.5× EBITDA. Safest debt stack here. | D11: 274.65 = Term Loan B principal ($m). Institutional loan below TLA, 1.5× EBITDA. Riskier than TLA, safer than Notes. | E11: 183.1 = Senior Notes principal ($m). Bond-style tranche, 1.0× EBITDA. Junior to TLA and TLB in repayment priority. | F11: Label | G11: Amount ($m)
B12: Rates — one interest rate per loan above | C12: 8.3% = TLA interest rate (SOFR+4.0%). Lowest spread of the loans because TLA is the senior bank piece. | D12: 9.3% = TLB interest rate (SOFR+5.0%). Higher than TLA because TLB lenders sit behind the bank loan. | E12: 7.8% = Notes interest rate (SOFR+3.5%). Rate charged on the $183.1m Notes principal in the cell above. | F12: Term Loan A principal | G12: 457.75
B13: How they differ: each column is a separate loan (TLA, TLB, Notes), not pieces of one TLA. Left=most senior; right=most junior. | C13: TLA vs others: TLA is the bank term loan — first claim on cash for interest and paydown. | D13: TLB vs others: TLB is the next loan — usually higher rate and paid after TLA. | E13: Notes vs others: Notes are the third stack — smallest dollars here; not a TLA sub-tranche. | F13: Term Loan B principal | G13: 274.65
F14: Senior Notes principal | G14: 183.1
F15: TOTAL DEBT | G15: 915.5
F16: Total debt = 457.75 + 274.65 + 183.10 = 915.50

Sheet Base_Operating
B2: Base case — no AI transformation
B3: Driver cells: Assumptions_Drivers!C5:C20
B4: Metric | C4: FY2024A | D4: Y1 2025 | E4: Y2 2026 | F4: Y3 2027 | G4: Y4 2028 | H4: Y5 2029
B5: Revenue | C5: 1214.3 | D5: 1275.015 | E5: 1338.7658 | F5: 1405.704 | G5: 1475.9892 | H5: 1549.7887
B6: COGS | C6: 242.86 | D6: 255.003 | E6: 267.75315 | F6: 281.14081 | G6: 295.19785 | H6: 309.95774
B7: Sales payroll (human) | C7: 289.9 | D7: 304.395 | E7: 319.61475 | F7: 335.59549 | G7: 352.37526 | H7: 369.99402
B8: Variable commissions | C8: 124.2 | D8: 130.41 | E8: 136.9305 | F8: 143.77703 | G8: 150.96588 | H8: 158.51417
B9: S&M human total | C9: 414.1 | D9: 434.805 | E9: 456.54525 | F9: 479.37251 | G9: 503.34114 | H9: 528.5082
B10: AI infrastructure | C10: 0 | D10: 0 | E10: 0 | F10: 0 | G10: 0 | H10: 0
B11: R&D | C11: 196.1 | D11: 205.905 | E11: 216.20025 | F11: 227.01026 | G11: 238.36078 | H11: 250.27881
B12: G&A (admin) | C12: 218.574 | D12: 229.5027 | E12: 240.97783 | F12: 253.02673 | G12: 265.67806 | H12: 278.96197
B13: EBITDA | C13: 183.1 | D13: 149.7993 | E13: 157.28927 | F13: 165.15373 | G13: 173.41141 | H13: 182.08199
B14: EBITDA margin | C14: 0.15078646 | D14: 0.11748826 | E14: 0.11748826 | F14: 0.11748826 | G14: 0.11748826 | H14: 0.11748826
B15: D&A | C15: 85.7 | D15: =C15*(1+Assumptions_Drivers!$C$5) -> 89.985 | E15: =D15*(1+Assumptions_Drivers!$C$5) -> 94.48425 | F15: =E15*(1+Assumptions_Drivers!$C$5) -> 99.208463 | G15: =F15*(1+Assumptions_Drivers!$C$5) -> 104.16889 | H15: =G15*(1+Assumptions_Drivers!$C$5) -> 109.37733
B16: EBIT | C16: 97.4 | D16: 59.8143 | E16: 62.805015 | F16: 65.945266 | G16: 69.242529 | H16: 72.704655
B17: Interest | D17: 77.8175 | E17: 72.807845 | F17: 66.808962 | G17: 59.710076 | H17: 51.555932
B18: Net income | D18: -18.0032 | E18: -10.00283 | F18: -0.86369656 | G18: 7.5306378 | H18: 16.707492
B19: CapEx | D19: =D5*Assumptions_Drivers!$C$24 -> 25.5003 | E19: =E5*Assumptions_Drivers!$C$24 -> 26.775315 | F19: =F5*Assumptions_Drivers!$C$24 -> 28.114081 | G19: =G5*Assumptions_Drivers!$C$24 -> 29.519785 | H19: =H5*Assumptions_Drivers!$C$24 -> 30.995774
B20: ΔNWC | D20: -13.875795 | E20: -14.569584 | F20: -15.298063 | G20: -16.062967 | H20: -16.866115
B21: FCF after interest | D21: 60.357295 | E21: 72.27569 | F21: 85.528749 | G21: 98.242705 | H21: 111.95516
B22: Mandatory amort | D22: 9.155 | E22: 9.155 | F22: 9.155 | G22: 9.155 | H22: 9.155
B23: Total debt paydown | D23: 60.357295 | E23: 72.27569 | F23: 85.528749 | G23: 98.242705 | H23: 111.95516
B24: Debt end | C24: 1329.9 | D24: 855.14271 | E24: 782.86702 | F24: 697.33827 | G24: 599.09556 | H24: 487.1404

Sheet AI_Operating
B2: AI-SDR case — drivers from Assumptions_Drivers
B3: Driver cells: Assumptions_Drivers!C5:C20
B4: Metric | C4: FY2024A | D4: Y1 2025 | E4: Y2 2026 | F4: Y3 2027 | G4: Y4 2028 | H4: Y5 2029
B5: Revenue | C5: 1214.3 | D5: 1275.015 | E5: 1338.7658 | F5: 1405.704 | G5: 1475.9892 | H5: 1549.7887
B6: COGS | C6: 242.86 | D6: 255.003 | E6: 267.75315 | F6: 281.14081 | G6: 295.19785 | H6: 309.95774
B7: Sales payroll (human) | C7: 289.9 | D7: 237.718 | E7: 242.47236 | F7: 247.32181 | G7: 252.26824 | H7: 257.31361
B8: Variable commissions | C8: 124.2 | D8: 101.844 | E8: 103.88088 | F8: 105.9585 | G8: 108.07767 | H8: 110.23922
B9: S&M human total | C9: 414.1 | D9: 339.562 | E9: 346.35324 | F9: 353.2803 | G9: 360.34591 | H9: 367.55283
B10: AI infrastructure | C10: 0 | D10: 24.5 | E10: 24.5 | F10: 24.5 | G10: 24.5 | H10: 24.5
B11: R&D | C11: 196.1 | D11: 205.905 | E11: 216.20025 | F11: 227.01026 | G11: 238.36078 | H11: 250.27881
B12: G&A (admin) | C12: 218.574 | D12: 229.5027 | E12: 240.97783 | F12: 253.02673 | G12: 265.67806 | H12: 278.96197
B13: EBITDA | C13: 183.1 | D13: 220.5423 | E13: 242.98128 | F13: 266.74594 | G13: 291.90664 | H13: 318.53735
B14: EBITDA margin | C14: 0.15078646 | D14: 0.17297232 | E14: 0.18149648 | F14: 0.18975967 | G14: 0.19777017 | H14: 0.20553599
B15: D&A | C15: 85.7 | D15: =C15*(1+Assumptions_Drivers!$C$5) -> 89.985 | E15: =D15*(1+Assumptions_Drivers!$C$5) -> 94.48425 | F15: =E15*(1+Assumptions_Drivers!$C$5) -> 99.208463 | G15: =F15*(1+Assumptions_Drivers!$C$5) -> 104.16889 | H15: =G15*(1+Assumptions_Drivers!$C$5) -> 109.37733
B16: EBIT | C16: 97.4 | D16: 130.5573 | E16: 148.49703 | F16: 167.53747 | G16: 187.73776 | H16: 209.16002
B17: Interest | D17: 77.8175 | E17: 67.60465 | F17: 55.208101 | G17: 40.395607 | H17: 20.877709
B18: Net income | D18: 41.664442 | E18: 63.904976 | F18: 88.740204 | G18: 116.4003 | H18: 148.74303
B19: CapEx | D19: =D5*Assumptions_Drivers!$C$24*(1-Assumptions_Drivers!$C$12) -> 23.460276 | E19: =E5*Assumptions_Drivers!$C$24*(1-Assumptions_Drivers!$C$12) -> 24.63329 | F19: =F5*Assumptions_Drivers!$C$24*(1-Assumptions_Drivers!$C$12) -> 25.864954 | G19: =G5*Assumptions_Drivers!$C$24*(1-Assumptions_Drivers!$C$12) -> 27.158202 | H19: =H5*Assumptions_Drivers!$C$24*(1-Assumptions_Drivers!$C$12) -> 28.516112
B20: ΔNWC | D20: -14.857215 | E20: -15.600076 | F20: -16.38008 | G20: -17.199084 | H20: -18.059038
B21: FCF after interest | D21: 123.04638 | E21: 149.35601 | F21: 178.46379 | G21: 210.61007 | H21: 247.66328 | J21: FCF≈NI+D&A−CapEx−ΔNWC (D&A IS added back; NI already deducted it).
B22: Mandatory amort | D22: 9.155 | E22: 9.155 | F22: 9.155 | G22: 9.155 | H22: 9.155
B23: Total debt paydown | D23: 123.04638 | E23: 149.35601 | F23: 178.46379 | G23: 210.61007 | H23: 247.66328
B24: Debt end | C24: 1329.9 | D24: 792.45362 | E24: 643.09761 | F24: 464.63382 | G24: 254.02375 | H24: 6.3604672

Sheet Coversheet
B2: vengeanceaiUSC-LBOMODEL4 — ZoomInfo (GTM) AI-SDR take-private
B8: LBO Model Sample Template
B11: Sample Modeling Template: The enclosed models are proprietary to Wall Street Prep and are designed for illustrative and training purposes only. Distributing, sharing, duplicating or altering these models in any way is prohibited without the written consent of Wall Street Prep, Inc. For more information about our training programs, please contact us at 800-646-3575 or visit us online at wallstreetprep.com.
B40: Open Strategy_Summary first — AI vs Base IRR and 500+ bps check
B41: AI IRR 16.9% vs Base 5.8% → +11.1 IRR points from AI S&M
B42: Y2 margin expansion 566 bps (target ≥500)

Sheet LBO
A1: GTM scrub: financing fees now on GTM principals; trans fee 2%×GTM offer; exit uses AI_Operating Y5 EBITDA + ~12.9x band; purchase price=H17; years retargeted off BMC 2011–2018. Deep IS/CF hist lines may still be template leftovers — operating thesis is AI_Operating / Debt_Sweep_AI.
B2: Leveraged buyout model for ZoomInfo (GTM) — vengeanceaiUSC-LBOMODEL4 AI-SDR
B3: $ mm except per share
B5: GENERAL INPUTS | F5: INITIAL VALUATION
B6: Company name | D6: ZoomInfo Technologies Inc.
B7: Ticker (if applicable) | D7: GTM | F7: Select a valuation approach: | H7: 1 | I7: 1 | J7: 2
B8: Current share price (if applicable) | D8: 4.05 | H8: Explicit offer/share | I8: Explicit EBITDA | J8: Explicit offer/share
B9: Latest closing share price date (f applicable) | D9: 45884 | E9: Modeled entry/close date set to 2025 (not calendar 2026) so Y1 2025 → exit YE 2029 is a clean 5-year hold.
B10: Circuit breaker: | D10: OFF | F10: LTM EBITDA | H10: 183.1 | I10: 183.1 | J10: 183.1
F11: EV / LTM EBITDA | H11: 14.78 | I11: 14.78 | J11: 14.78
B12: SELECT FINANCIAL DATA / ASSMUPTIONS | F12: Enterprise value | H12: 2705.6759 | I12: 2705.6759 | J12: 2705.6759
B13: EBITDA (LTM) | D13: 183.1
B14: Gross Debt (input as a -) | D14: -1329.9 | F14: Less: Gross Debt (latest filing) | H14: -1329.9 | I14: -1329.9 | J14: -1329.9
B15: Cash | D15: 179.9 | F15: Plus: Cash (latest filing) | H15: 179.9 | I15: 179.9 | J15: 179.9
B16: Minimum cash desired | D16: 50
B17: EV / LTM EBITDA multiple at exit | D17: 12.9 | F17: Offer value | H17: 1555.6759 | I17: 1555.6759 | J17: 1555.6759
F18: Diluted shares outstanding | H18: 307.294 | I18: 307.294 | J18: 307.294
B19: USES OF FUNDS
B20: Buyout of equity | D20: 1555.7 | F20: Offer value / per share | H20: 5.0625 | I20: 5.0625 | J20: 5.0625
B21: Refinancing of oldco debt | D21: 1329.9 | F21: % Premium / discount | H21: 0.25 | I21: 0.25 | J21: 0.25
B22: Fees (transaction & financing) | D22: =H33+H36 -> 43.932018 | E22: Fees = GTM financing (∑ %×principal ≈ $12.8m) + transaction 2%×offer ≈ $31.1m → ≈ $43.9m. Prior ~$69.7m financing used BMC loan notionals.
B23: Total Uses | D23: =D20+D21+D22 -> 2929.532
B25: SOURCES OF FUNDS | F25: FEES
C26: EBITDA turns | D26: $ investment | G26: % fees | H26: Fee | I26: Term | J26: Fee amort / year
B27: Excess cash | C27: 0.7094 | D27: 129.9 | E27: Side note: Excess cash comes directly from the target company. In an LBO model, it represents existing balance sheet cash above minimum operating needs, utilized to help fund the transaction. | F27: Financing fees
B28: Revolver | C28: 0 | D28: 0 | F28: Revolver | G28: 0.01 | H28: =G28*D28 -> 0 | I28: 5 | J28: =IF(OR(I28="",I28=0),0,H28/I28) -> 0
B29: Term Loan A | C29: 2.5 | D29: 457.8 | F29: Term Loan A | G29: 0.015 | H29: =G29*D29 -> 6.867 | I29: 7 | J29: =IF(OR(I29="",I29=0),0,H29/I29) -> 0.981
B30: Term Loan B | C30: 1.5 | D30: 274.7 | F30: Term Loan B | G30: 0.015 | H30: =G30*D30 -> 4.1205 | I30: 7 | J30: =IF(OR(I30="",I30=0),0,H30/I30) -> 0.58864286
B31: Senior Note | C31: 1 | D31: 183.1 | F31: Senior Note | G31: 0.01 | H31: =G31*D31 -> 1.831 | I31: 8 | J31: =IF(OR(I31="",I31=0),0,H31/I31) -> 0.228875
B32: Sub Note | C32: 0 | D32: 0 | F32: Sub Note | G32: 0 | H32: =G32*D32 -> 0 | J32: NM
B33: Preferred stock | C33: 0 | D33: 0 | F33: Financing fees | H33: =SUM(H28:H32) -> 12.8185 | J33: =SUM(J28:J32) -> 1.7985179
B34: Mgmt rollover | C34: 0 | D34: 0
B35: Sponsor equity | C35: =IF(D13=0,0,D35/D13) -> 10.289634 | D35: =D23-SUM(D27:D34) -> 1884.032 | E35: Side note: Sponsor equity ≈ $1,884.0m (≈10.29x LTM EBITDA $183.1m, not exit). D35 plugs so Sources = Uses. | G35: % of offer value | H35: Fee
B36: Total Sources | C36: =SUM(C27:C35) -> 15.999034 | D36: =SUM(D27:D35) -> 2929.532 | F36: Trans. fees | G36: 0.02 | H36: =G36*H17 -> 31.113518
E37: =IF(ABS(H37)<0.01,"BALANCED","MISMATCH") -> BALANCED | F37: Sources − Uses (should be 0) | H37: =D36-D23 -> 0
A38: x | B38: INCOME STATEMENT | L38: IS commentary (≤~30 words) — GTM AI-SDR thesis
B39: Fiscal year | C39: 2022 | D39: 2023 | E39: 2024 | F39: 2025 | G39: 2026 | H39: 2027 | I39: 2028 | J39: 2029
B40: Fiscal year end date | C40: 44926 | D40: 45291 | E40: 45657 | F40: 46022 | G40: 46387 | H40: 46752 | I40: 47118 | J40: 47483
B42: Revenue | C42: 2065.3 | D42: 2172 | E42: 2201.4 | F42: 1250.7 | G42: 1300.8 | H42: 1352.8 | I42: 1393.4 | J42: 1435.2 | L42: Revenue: GTM thesis keeps modest +5% growth (Drivers). Top line is not the lever—AI-SDR value is cost takeout, so revenue mainly scales the margin and FCF story.
B43: Cost of sales (enter as -) | C43: -485.2 | D43: -568.9 | E43: -592 | F43: -195.5 | G43: -203.3 | H43: -211.4 | I43: -217.8 | J43: -224.3
B44: Gross Profit | C44: 1580.1 | D44: 1603.1 | E44: 1609.4 | F44: 1696.8568 | G44: 1802.2027 | H44: 1923.0749 | I44: 2032.6055 | J44: 2144.1896 | L44: Gross profit: Model uses ~80% software median GM (Drivers), below ZI’s higher GAAP GM. Gross margin sets the ceiling before S&M/AI opex hits EBITDA.
B45: Research & development (enter as -) | C45: -181.6 | D45: -165.2 | E45: -174.6 | F45: -202 | G45: -210.1 | H45: -218.5 | I45: -225 | J45: -231.8
B46: Selling, general & administrative (enter as -) | C46: -865.7 | D46: -894 | E46: -969.4 | F46: -601.4 | G46: -617.6 | H46: -634.3 | I46: -649.2 | J46: -664.4 | L46: SG&A: Most impactful P&L lever. Y1 cuts human S&M payroll/commissions 18%, adds $24.5m AI cost; Y2+ S&M grows only ~2%, expanding EBITDA margin vs Base.
B47: Deal-related D&A (enter as -) | F47: -52.997322 | G47: -52.997322 | H47: -52.997322 | I47: -52.997322 | J47: -52.997322
B48: Operating profit (EBIT) | C48: 532.8 | D48: 543.9 | E48: 465.4 | F48: 163.6 | G48: 178 | H48: 193.1 | I48: 203.1 | J48: 213.4 | L48: EBIT: After D&A/deal D&A, operating profit converts AI S&M savings into earnings power. Watch that template hist EBIT still mixes old rows—forecast EBITDA is linked to AI_Operating.
B49: Interest income | C49: 15 | D49: 10.6 | E49: 8.3 | F49: 0.92867133 | G49: 0.92867133 | H49: 0.92867133 | I49: 0.92867133 | J49: 0.92867133
B50: Interest expense (enter as -) | C50: -19.8 | D50: -23.3 | E50: -47.8 | F50: -68.7 | G50: -58.3 | H50: -46.4 | I50: -32.7 | J50: -17.3 | L50: Interest expense: Second cash lever. Higher early interest on new LBO stack falls as FCF sweeps debt (Debt_Sweep_AI)—AI case nearly clears debt by 2029, juicing exit equity.
B51: Other non-operating expense (enter as -) | C51: 3.3 | D51: -1.2 | E51: 2 | F51: 0 | G51: 0 | H51: 0 | I51: 0 | J51: 0
B52: Pretax profit | C52: 531.3 | D52: 530 | E52: 427.9 | F52: 197.66772 | G52: 284.77783 | H52: 378.81301 | I52: 479.27035 | J52: 596.38266
B53: Taxes (enter expense as -) | C53: -75.1 | D53: -129 | E53: -96.9 | F53: -44.762801 | G53: -64.4893 | H53: -85.784016 | I53: -108.53306 | J53: -135.0537
B54: Net income | C54: 456.2 | D54: 401 | E54: 331 | F54: 75 | G54: 94.5 | H54: 115.9 | I54: 134.6 | J54: 154.9 | L54: Net income: Bottom-line after tax; less central than EBITDA/FCF for LBO returns, but shows AI case turning positive sooner as interest falls and margins expand.
B56: EBITDA reconciliation
B57: EBIT (GAAP) | C57: 532.8 | D57: 543.9 | E57: 465.4 | F57: 493.68031 | G57: 559.80404 | H57: 634.79196 | I57: 709.31226 | J57: 787.96024
B58: Depreciation and amortization | C58: 190 | D58: 224.6 | E58: 229 | F58: =AI_Operating!D15 -> 89.985 | G58: =AI_Operating!E15 -> 94.48425 | H58: =AI_Operating!F15 -> 99.208463 | I58: =AI_Operating!G15 -> 104.16889 | J58: =AI_Operating!H15 -> 109.37733
B59: Deal-related D&A | F59: 52.997322 | G59: 52.997322 | H59: 52.997322 | I59: 52.997322 | J59: 52.997322
B60: Stock based compensation | C60: 106.5 | D60: 127.2 | E60: 147.4 | F60: =F70*(-F43-F45-F46) -> 140.8449 | G60: =G70*(-G43-G45-G46) -> 145.371 | H60: =H70*(-H43-H45-H46) -> 150.0522 | I60: =I70*(-I43-I45-I46) -> 153.972 | J60: =J70*(-J43-J45-J46) -> 157.9905 | L60: SBC $ now = F70 × (|COS|+|R&D|+|SG&A|). Driven by Assumptions_Drivers!C29 (14.1%).
B61: Restructuring and other nonrecurring charges | C61: 14.3 | D61: 10.8 | E61: 40.9 | F61: 16 | G61: 5 | H61: 5 | I61: 0 | J61: 0
B62: EBITDA | C62: 843.6 | D62: 906.5 | E62: 882.7 | F62: =AI_Operating!D13 -> 220.5423 | G62: =AI_Operating!E13 -> 242.98128 | H62: =AI_Operating!F13 -> 266.74594 | I62: =AI_Operating!G13 -> 291.90664 | J62: =AI_Operating!H13 -> 318.53735 | L62: EBITDA: Primary LBO earnings metric. Forecast F–J link to AI_Operating (AI-SDR case). Exit EV = Y5 EBITDA × 12.9x—margin expansion here drives MOIC/IRR vs Base.
L63: Growth trajectory (figure FIRST) | M63: SOURCE (click) — Assess + how number enters | N63: VERBATIM Ctrl+F + EQ derivation (how the % was calculated) | O63: WHY REASONABLE (≤30 words) — where the number came from
B64: Growth rates & margins | K64: Step | L64: Figure first: +5%, 80% flat, etc. | M64: Growth rates & margins — each forecast % must show source quote + arithmetic (EQ)
B65: Revenue growth | D65: 0.051663197 | E65: 0.013535912 | F65: =Assumptions_Drivers!$C$5 -> 0.05 | G65: =Assumptions_Drivers!$C$5 -> 0.05 | H65: =Assumptions_Drivers!$C$5 -> 0.05 | I65: =Assumptions_Drivers!$C$5 -> 0.05 | J65: =Assumptions_Drivers!$C$5 -> 0.05 | K65: 0 | L65: +5%/yr flat (Drivers C5). Same growth rate every forecast year — not the FY25 +3% print; rounded 2022–25 CAGR ~4.4% → +5%. | M65: =HYPERLINK("https://www.sec.gov/Archives/edgar/data/1794515/000179451526000012/zi-20251231.htm","REASONABLE: ZI FY25 10-K — Drivers C5=+5% (rounded CAGR, not raw +3%)") -> REASONABLE: ZI FY25 10-K — Drivers C5=+5% (rounded CAGR, not raw +3%) | N65: Ctrl+F: Revenue was $1,249.5 million for the year ended December 31, 2025, an increase of $35.2 million, or 3% EQ: FY22 rev $1,098.0 → FY25 $1,249.5; CAGR=(1249.5/1098)^(1/3)−1≈4.4% → Drivers C5 rounds to +5%. LBO F65:J65 = Assumptions_Drivers!$C$5. | O65: +5% enters via Drivers C5. 10-K shows FY25 +3%; model uses rounded multi-year CAGR ~4.4%.
B66: Gross profit as % of sales | C66: 0.76507045 | D66: 0.73807551 | E66: 0.73108022 | F66: =Assumptions_Drivers!$C$6 -> 0.8 | G66: =Assumptions_Drivers!$C$6 -> 0.8 | H66: =Assumptions_Drivers!$C$6 -> 0.8 | I66: =Assumptions_Drivers!$C$6 -> 0.8 | J66: =Assumptions_Drivers!$C$6 -> 0.8 | K66: 0 | L66: 80% flat every year (Drivers C6). GM ratio does not trend up/down; dollars of GP grow ~+5% with sales at constant 80%. | M66: =HYPERLINK("https://www.getaleph.com/answers/saas-gross-margin-2026","REASONABLE: Aleph × Benchmarkit — median GM 80% → Drivers C6") -> REASONABLE: Aleph × Benchmarkit — median GM 80% → Drivers C6 | N66: Ctrl+F: The 2025 median software gross margin is 80% EQ: Drivers C6 = 80% exactly from that median sentence. LBO F66:J66 = Assumptions_Drivers!$C$6. (ZI GAAP GM ~84% is NOT the driver.) | O66: 80% is Aleph’s median and Drivers C6; that flat 80% feeds every forecast GM cell.
B67: R&D margin | C67: 0.087929114 | D67: 0.076058932 | E67: 0.079313164 | F67: =IF(AI_Operating!F5=0,0,AI_Operating!F11/AI_Operating!F5) -> 0.16149222 | G67: =IF(AI_Operating!G5=0,0,AI_Operating!G11/AI_Operating!G5) -> 0.16149222 | H67: =IF(AI_Operating!H5=0,0,AI_Operating!H11/AI_Operating!H5) -> 0.16149222 | I67: =IF(AI_Operating!I5=0,0,AI_Operating!I11/AI_Operating!I5) -> 0 | J67: =IF(AI_Operating!J5=0,0,AI_Operating!J11/AI_Operating!J5) -> 0 | K67: 0 | L67: ~16.15% flat (R&D÷Sales). FY24 $196.1÷$1,214.3; both scale +5% in AI_Operating so the margin stays constant. | M67: =HYPERLINK("https://www.sec.gov/Archives/edgar/data/1794515/000179451525000045/zi-20241231.htm","REASONABLE: ZI FY24 10-K — R&D $196.1m / Rev $1,214.3m ≈16.15%") -> REASONABLE: ZI FY24 10-K — R&D $196.1m / Rev $1,214.3m ≈16.15% | N67: Ctrl+F: Research and development for the year ended December 31, 2024 was $196.1 million Ctrl+F: Revenue was $1,214.3 million for the year ended December 31, 2024 EQ: 196.1÷1,214.3≈16.15%. AI_Operating grows both at +5%, so R&D% stays ~16.15%. LBO = AI_Operating!R&D / AI_Operating!Revenue. | O67: 16.15% from FY24 R&D÷sales; held flat by growing R&D with +5% revenue in AI_Operating.
B68: SG&A margin | C68: 0.41916429 | D68: 0.41160221 | E68: 0.44035614 | F68: =IF(AI_Operating!F5=0,0,(AI_Operating!F9+AI_Operating!F10+AI_Operating!F12)/AI_Operating!F5) -> 0.44874811 | G68: =IF(AI_Operating!G5=0,0,(AI_Operating!G9+AI_Operating!G10+AI_Operating!G12)/AI_Operating!G5) -> 0.44073761 | H68: =IF(AI_Operating!H5=0,0,(AI_Operating!H9+AI_Operating!H10+AI_Operating!H12)/AI_Operating!H5) -> 0.43297179 | I68: =IF(AI_Operating!I5=0,0,(AI_Operating!I9+AI_Operating!I10+AI_Operating!I12)/AI_Operating!I5) -> 0 | J68: =IF(AI_Operating!J5=0,0,(AI_Operating!J9+AI_Operating!J10+AI_Operating!J12)/AI_Operating!J5) -> 0 | K68: 0 | L68: −18% S&M cut in Y1, then S&M +2%/yr (Fed); G&A flat 18% of sales; +$24.5m AI each year. SG&A% = (S&M+AI+G&A)/Sales from AI_Operating. | M68: =HYPERLINK("https://www.digitalapplied.com/blog/ai-sdr-statistics-2026-outbound-sales-data-points","REASONABLE: Built %, not one page — 18% SDR cut (Digital Applied) + G&A 18% (Blossom) + $24.5m AI") -> REASONABLE: Built %, not one page — 18% SDR cut (Digital Applied) + G&A 18% (Blossom) + $24.5m AI | N68: Ctrl+F (Digital Applied): Net SDR headcount in US B2B SaaS companies is down 18% YoY Ctrl+F (Blossom, Drivers E11): G&A was 18% EQ: SG&A% = (S&M_human + AI_infra $24.5m + G&A)/Revenue from AI_Operating. S&M_human = FY24 $414.1m×(1−18%); G&A = 18%×Revenue. | O68: −18% is the Y1 S&M lever; SG&A% is built in AI_Operating, not a single page quote.
B69: Tax rate | C69: 0.1413514 | D69: 0.24339623 | E69: 0.22645478 | F69: =Assumptions_Drivers!$C$19 -> 0.21 | G69: =Assumptions_Drivers!$C$19 -> 0.21 | H69: =Assumptions_Drivers!$C$19 -> 0.21 | I69: =Assumptions_Drivers!$C$19 -> 0.21 | J69: =Assumptions_Drivers!$C$19 -> 0.21 | K69: 0 | L69: 21% flat every year (Drivers C19). Statutory rate — no glide path; tax $ grows with pretax income, rate unchanged. | M69: =HYPERLINK("https://taxsummaries.pwc.com/united-states/corporate/taxes-on-corporate-income","REASONABLE: PwC — flat 21% → Drivers C19") -> REASONABLE: PwC — flat 21% → Drivers C19 | N69: Ctrl+F: The United States taxes resident corporations at a flat rate of 21% EQ: Drivers C19 = 21% from that sentence. LBO F69:J69 = Assumptions_Drivers!$C$19. | O69: 21% is PwC’s flat federal rate in Drivers C19; this row links straight to that cell.
B70: SBC as % of all operating expenses | C70: 0.06949429 | D70: 0.078127879 | E70: 0.084907834 | F70: =Assumptions_Drivers!$C$29 -> 0.141 | G70: =Assumptions_Drivers!$C$29 -> 0.141 | H70: =Assumptions_Drivers!$C$29 -> 0.141 | I70: =Assumptions_Drivers!$C$29 -> 0.141 | J70: =Assumptions_Drivers!$C$29 -> 0.141 | K70: 0 | L70: 14.1% flat (Drivers C29). FY25 $116.2÷$824.2; SBC $ = 14.1%×opex each year. DCF add-back stays $0. | M70: =HYPERLINK("https://www.sec.gov/Archives/edgar/data/1794515/000179451526000012/zi-20251231.htm","CAUTION — Drivers C29: FY25 SBC $116.2m ÷ opex $824.2m = 14.1%; LBO $ = %×opex") -> CAUTION — Drivers C29: FY25 SBC $116.2m ÷ opex $824.2m = 14.1%; LBO $ = %×opex | N70: Ctrl+F: Total equity-based compensation expense $ 116.2 Ctrl+F: Total operating expenses $ 824.2 EQ: Drivers C29=116.2÷824.2=14.1%. LBO F70:J70=Assumptions_Drivers!$C$29. SBC $=F70×(|F43|+|F45|+|F46|); CF F118=F60. | O70: 14.1% from FY25 SBC÷opex in Drivers C29; LBO $ and CF linked. DCF add-back stays 0.
B72: WORKING CAPITAL | L72: How each WC line grows (or stays flat) in the forecast. | M72: WORKING CAPITAL — forecast % linked to Drivers (same standard as IS margins). Core LBO FCF uses AI_Operating ΔNWC = ΔAR−ΔDeferred.
B73: Fiscal year | C73: 2022 | D73: 2023 | E73: 2024 | F73: 2025 | G73: 2026 | H73: 2027 | I73: 2028 | J73: 2029
B74: Fiscal year end date | D74: 45291 | E74: 45657 | F74: 46022 | G74: 46387 | H74: 46752 | I74: 47118 | J74: 47483
L75: Growth trajectory (figure FIRST) | M75: SOURCE (click) — Assess + how number enters | N75: VERBATIM Ctrl+F + EQ derivation | O75: WHY REASONABLE (≤30 words) | P75: Major Variable — NET + or NET − for LBO
B76: Accounts receivable, EOP | D76: 484.8 | E76: 443.7 | F76: =F77*F42 -> 202.16795 | G76: =G77*G42 -> 210.2663 | H76: =H77*H42 -> 218.67178 | I76: =I77*I42 -> 225.23452 | J76: =J77*J42 -> 231.99123 | L76: +5%/yr. EOP AR = flat 16.2% × Sales; dollars track revenue growth; AR% does not trend. AI FCF: ΔAR = ΔRev×16.2%×(1−10%). | M76: =HYPERLINK("https://www.sec.gov/Archives/edgar/data/1794515/000179451525000045/zi-20241231.htm","REASONABLE: EOP AR = Drivers C25 × Revenue (stock from intensity)") -> REASONABLE: EOP AR = Drivers C25 × Revenue (stock from intensity) | N76: Ctrl+F: Accounts receivable, net | 246.1 EQ: F76=F77×F42. F77=Assumptions_Drivers!$C$25 (59/365). AI FCF uses ΔAR=ΔRev×C25×(1−C13), not this EOP alone. | O76: EOP AR rebuilt as intensity×sales so the BS tracks Drivers. Live debt-sweep cash uses AI_Operating ΔAR, not BMC AR. | P76: YES — NET − for LBO. Higher AR ties cash; ΔAR is a cash use that slows debt paydown / IRR.
B77: AR as % of sales (Drivers C25 intensity) | D77: 0.22320442 | E77: 0.20155356 | F77: =Assumptions_Drivers!$C$25 -> 0.16164384 | G77: =Assumptions_Drivers!$C$25 -> 0.16164384 | H77: =Assumptions_Drivers!$C$25 -> 0.16164384 | I77: =Assumptions_Drivers!$C$25 -> 0.16164384 | J77: =Assumptions_Drivers!$C$25 -> 0.16164384 | L77: 16.2% flat every year (Drivers C25). Ratio does not grow; dollar AR grows only because sales grow +5%. AI ΔAR intensity = 16.2%×90% = 14.55%. | M77: =HYPERLINK("https://getfairview.com/blog/working-capital-management-saas","REASONABLE: Fairview median DSO 59d → C25=59/365≈16.2%") -> REASONABLE: Fairview median DSO 59d → C25=59/365≈16.2% | N77: Ctrl+F: Median B2B SaaS DSO is 59 days EQ: Assumptions_Drivers!C25=59/365≈16.164%. LBO F77:J77=Assumptions_Drivers!$C$25. AI also applies C13=10% cut on ΔAR only. | O77: Fairview’s 59-day median becomes 16.2% AR intensity in Drivers C25; that cell feeds every forecast AR% here. | P77: YES — NET − for LBO at 16.2% intensity (cash use on growth). AI C13 softens it; still an AR drag vs deferred.
B78: Other current assets, EOP | D78: 195.1 | E78: 213.1 | F78: =F79*F42 -> 121.07031 | G78: =G79*G42 -> 125.92009 | H78: =H79*H42 -> 130.95379 | I78: =I79*I42 -> 134.88396 | J78: =J79*J42 -> 138.93028 | L78: +5%/yr. EOP = flat 9.7% × Sales → dollars track sales. “Flat” = the 9.7% ratio stays unchanged (no step-up/fade). | M78: =HYPERLINK("https://www.sec.gov/Archives/edgar/data/1794515/000179451525000045/zi-20241231.htm","CAUTION — not a Driver: other CA held at FY24 % of sales") -> CAUTION — not a Driver: other CA held at FY24 % of sales | N78: Ctrl+F: Prepaid expenses and other current assets (ZI BS) EQ: Hold E79≈9.7% of sales flat; F78=F79×F42. Not in AI_Operating ΔNWC math (ΔNWC≈ΔAR−ΔDeferred only). | O78: Flat means the % does not trend. Only the dollar balance rises because sales rise +5%; ratio locked at ~9.7%. | P78: NO — n/a sign. Not in AI ΔNWC; immaterial to LBO FCF/IRR.
B79: Other current assets as % of sales | D79: 0.089825046 | E79: 0.096802035 | F79: 0.096802035 | G79: 0.096802035 | H79: 0.096802035 | I79: 0.096802035 | J79: 0.096802035 | L79: 9.7% flat every forecast year. Not growing as a percentage; only $ Other CA grow when sales grow +5%. | M79: =HYPERLINK("https://www.sec.gov/Archives/edgar/data/1794515/000179451525000045/zi-20241231.htm","CAUTION — not a Driver: other CA % held flat") -> CAUTION — not a Driver: other CA % held flat | N79: EQ: F79:J79 = E79 (last hist %). Not Assumptions_Drivers. Core model ignores other CA in ΔNWC. | O79: Flat ratio = no YoY change in %. Placeholder hist hold; dollars move only with +5% sales. | P79: NO — n/a sign. Non-core; no Drivers link.
B80: Accounts payable, EOP | D80: 32.7 | E80: 42.1 | F80: =F81*(-F43) -> 13.902956 | G80: =G81*(-G43) -> 14.457652 | H80: =H81*(-H43) -> 15.033682 | I80: =I81*(-I43) -> 15.488818 | J80: =J81*(-J43) -> 15.951064 | L80: +5%/yr. EOP AP = flat 7.1% × |COGS|; COGS also rises ~+5% with sales. Ratio flat; dollars ≈+5%. | M80: =HYPERLINK("https://www.sec.gov/Archives/edgar/data/1794515/000179451525000045/zi-20241231.htm","CAUTION — ZI AP only $16.6m; hold hist AP/COGS %") -> CAUTION — ZI AP only $16.6m; hold hist AP/COGS % | N80: Ctrl+F: Accounts payable | $16.6 EQ: F81 held at E81; F80=F81×|COGS|. SaaS AP is tiny vs deferred revenue; not a Drivers lever. | O80: ZI FY24 AP was $16.6m — small. Held hist AP/COGS %. Not a core LBO cash lever vs deferred/AR. | P80: NO — n/a sign. Small SaaS AP; weak FCF/IRR sensitivity.
B81: AP as % of COGS | D81: 0.057479346 | E81: 0.071114865 | F81: 0.071114865 | G81: 0.071114865 | H81: 0.071114865 | I81: 0.071114865 | J81: 0.071114865 | L81: 7.1% flat every year (AP/COGS). No DPO improvement. Dollars grow only as COGS grows ~+5% with sales. | M81: =HYPERLINK("https://www.sec.gov/Archives/edgar/data/1794515/000179451525000045/zi-20241231.htm","CAUTION — not a Driver: AP/COGS % held flat") -> CAUTION — not a Driver: AP/COGS % held flat | N81: Ctrl+F: Accounts payable | $16.6 EQ: F81:J81 = E81. No Assumptions_Drivers cell for DPO/AP%. | O81: AP% is residual hist, not a sourced Driver. Core NWC thesis is AR + deferred, not payables. | P81: NO — n/a sign. Not a Drivers assumption.
B82: Accrued expenses & def revenues, EOP | D82: 2313.3 | E82: 2301.7 | F82: =F83*F42 -> 488.00268 | G82: =G83*G42 -> 507.55089 | H82: =H83*H42 -> 527.84043 | I82: =I83*I42 -> 543.68189 | J82: =J83*J42 -> 559.99157 | L82: +5%/yr. EOP deferred/accrued = flat 39.0% × Sales; $ balance rises with sales. ΔDeferred = 39%×ΔRev each year (cash source). | M82: =HYPERLINK("https://www.sec.gov/Archives/edgar/data/1794515/000179451525000045/zi-20241231.htm","REASONABLE: EOP deferred/accrued ≈ Drivers C26 × Revenue") -> REASONABLE: EOP deferred/accrued ≈ Drivers C26 × Revenue | N82: Ctrl+F: we had unearned revenue of $477.9 million, of which $473.8 million was recorded as a current liability EQ: F82=F83×F42; F83=Assumptions_Drivers!$C$26. ΔDeferred≈C26×ΔRev is the cash-source leg of AI ΔNWC. | O82: EOP deferred rebuilt from Drivers 39% so BS matches the unearned-revenue cash source in FCF math. | P82: YES — NET + for LBO. Deferred/unearned is the largest SaaS cash source; funds FCF and debt sweep.
B83: Deferred/accrued as % of sales (Drivers C26) | D83: 1.0650552 | E83: 1.0455619 | F83: =Assumptions_Drivers!$C$26 -> 0.39018364 | G83: =Assumptions_Drivers!$C$26 -> 0.39018364 | H83: =Assumptions_Drivers!$C$26 -> 0.39018364 | I83: =Assumptions_Drivers!$C$26 -> 0.39018364 | J83: =Assumptions_Drivers!$C$26 -> 0.39018364 | L83: 39% flat of sales all years (Drivers C26). Dollars grow only via +5% revenue. No fade or step-up in deferred attach. | M83: =HYPERLINK("https://www.sec.gov/Archives/edgar/data/1794515/000179451525000045/zi-20241231.htm","REASONABLE: ZI FY24 unearned $473.8m / sales $1,214.3m → C26≈39%") -> REASONABLE: ZI FY24 unearned $473.8m / sales $1,214.3m → C26≈39% | N83: Ctrl+F: 473.8 Ctrl+F: Unearned revenue, current portion EQ: Assumptions_Drivers!C26=473.8/1,214.3≈39.02%. LBO F83:J83=Assumptions_Drivers!$C$26. | O83: 10-K current unearned $473.8m ÷ FY24 sales $1,214.3m = 39%. That exact ratio is Drivers C26. | P83: YES — NET + for LBO. 39% deferred intensity → ΔDeferred cash inflow dominates ΔNWC.
B85: Net Working Capital (EOP) | D85: -1666.1 | E85: -1687 | F85: =F76+F78-F80-F82 -> -178.66739 | G85: =G76+G78-G80-G82 -> -185.82215 | H85: =H76+H78-H80-H82 -> -193.24854 | I85: =I76+I78-I80-I82 -> -199.05223 | J85: =J76+J78-J80-J82 -> -205.02112 | L85: −24.45% of ΔRev/yr (AI). NWC more negative as sales grow +5%: deferred 39% > AR 16.2%×(1−10%). ΔNWC ≈ ΔRev×[14.55%−39%]. | M85: =HYPERLINK("https://getfairview.com/blog/working-capital-management-saas","REASONABLE: EOP NWC = AR+OCA−AP−Deferred; FCF uses AI ΔNWC") -> REASONABLE: EOP NWC = AR+OCA−AP−Deferred; FCF uses AI ΔNWC | N85: EQ: F85=F76+F78−F80−F82. Core LBO/DCF cash: AI_Operating ΔNWC≈ΔAR−ΔDeferred with ΔAR=ΔRev×C25×(1−C13), ΔDef=ΔRev×C26. CF row F119=AI_Operating ΔNWC. | O85: EOP NWC is the BS rollup. Deal cash and debt sweep follow AI_Operating ΔNWC from Drivers C13/C25/C26. | P85: YES — NET + for LBO. AI ΔNWC ≈ −24.5% of ΔRev (cash release) → more sweep / higher IRR.
B86: AI AR improvement (Drivers C13) — applies in AI_Operating ΔNWC | L86: −10% once (Drivers C13). Permanent lower ΔAR intensity from Y1 — not another −10% each year. Base 16.2%×ΔRev; AI 14.55%×ΔRev. | M86: =HYPERLINK("https://getfairview.com/blog/working-capital-management-saas","RELATED Drivers C13: 10% AR/DSO improvement — MAJOR AI lever") -> RELATED Drivers C13: 10% AR/DSO improvement — MAJOR AI lever | N86: Ctrl+F: Median B2B SaaS DSO is 59 days EQ: Drivers C13=10%. Model story: ~6/59≈10% DSO cut → ΔAR_AI=ΔRev×C25×(1−0.10). Applies to AI_Operating only (not Base). | O86: 10% cuts ΔAR only (not whole NWC). With deferred still at 39%, net ΔNWC stays a cash source. | P86: YES — NET + for LBO. −10% ΔAR cut vs Base frees cash and lifts AI FCF / debt paydown.
B87: LONG LIVED ASSETS | L87: Assets — CapEx/D&A wired to Drivers/AI_Operating (was BMC). Intangible & capitalized-software buys set to $0 to match DCF.
B88: Fiscal year | C88: 2022 | D88: 2023 | E88: 2024 | F88: 2025 | G88: 2026 | H88: 2027 | I88: 2028 | J88: 2029
B89: Fiscal year end date | C89: 44926 | D89: 45291 | E89: 45657 | F89: 46022 | G89: 46387 | H89: 46752 | I89: 47118 | J89: 47483
L90: Growth trajectory (figure FIRST) | M90: SOURCE (click) — Assess + how number enters | N90: VERBATIM Ctrl+F + EQ derivation | O90: WHY REASONABLE (≤30 words) — LBO impact | P90: Major Variable — NET + or NET − for LBO
B91: PP&E | D91: 87.8 | E91: 85.2 | F91: =E91+F92+F93 -> 18.675276 | G91: =F91+G92+G93 -> -51.175684 | H91: =G91+H92+H93 -> -124.51919 | I91: =H91+I92+I93 -> -201.52988 | J91: =I91+J92+J93 -> -282.39109 | L91: +5%/yr sales-linked. PP&E rolls: prior + CapEx − D&A. Net book often falls if D&A > CapEx (SaaS asset-light). | M91: =HYPERLINK("https://saasdb.app/learn/financials/fcf-margin/","REASONABLE: PPE roll follows CapEx/D&A; SaaS is asset-light") -> REASONABLE: PPE roll follows CapEx/D&A; SaaS is asset-light | N91: Ctrl+F: CapEx of 1–3% of revenue — primarily laptops, office equipment EQ: F91=E91+F92+F93 with F92=AI CapEx, F93=−AI D&A. | O91: PP&E is the balance sheet roll of CapEx/D&A. LBO cash cares about CapEx outlay, not PPE level. | P91: NO — n/a sign. BS stock; cash impact is CapEx (row 92).
B92: Capital expenditures | C92: 22 | D92: 26.5 | E92: 24.5 | F92: =AI_Operating!D19 -> 23.460276 | G92: =AI_Operating!E19 -> 24.63329 | H92: =AI_Operating!F19 -> 25.864954 | I92: =AI_Operating!G19 -> 27.158202 | J92: =AI_Operating!H19 -> 28.516112 | L92: 1.84% of sales/yr (=2%×(1−8%)). Dollars grow ~+5% with revenue. Was wrong BMC $26–31m — now AI_Operating CapEx. | M92: =HYPERLINK("https://saasdb.app/learn/financials/fcf-margin/","REASONABLE: Drivers C24=2% mid of 1–3%; AI cut C12=8% → 1.84%") -> REASONABLE: Drivers C24=2% mid of 1–3%; AI cut C12=8% → 1.84% | N92: Ctrl+F: Most pure-play SaaS companies report CapEx of 1–3% of revenue Ctrl+F: primarily laptops, office equipment EQ: CapEx=Rev×C24×(1−C12)=Rev×1.84%. LBO F92=AI_Operating CapEx; DCF! CapEx same link. | O92: 1.84% CapEx directly reduces UFCF/FCF and cash for debt sweep — core LBO cash outflow. | P92: YES — NET − for LBO. CapEx is a cash outflow that reduces FCF available for debt paydown / IRR.
B93: Depreciation | C93: -39.1 | D93: -37.8 | E93: -38.7 | F93: =-AI_Operating!D15 -> -89.985 | G93: =-AI_Operating!E15 -> -94.48425 | H93: =-AI_Operating!F15 -> -99.208463 | I93: =-AI_Operating!G15 -> -104.16889 | J93: =-AI_Operating!H15 -> -109.37733 | L93: +5%/yr. D&A grows with sales from FY24 $85.7m. Major FCF point: IS deducts it; FCF adds it back (non-cash). | M93: =HYPERLINK("https://www.sec.gov/Archives/edgar/data/1794515/000179451525000045/zi-20241231.htm","REASONABLE: FY24 D&A anchor $85.7m; grow at Drivers +5%") -> REASONABLE: FY24 D&A anchor $85.7m; grow at Drivers +5% | N93: Ctrl+F: depreciation and amortization (ZI cash flow / notes) EQ: AI D15=C15×(1+C5). DCF Unlevered CFO = EBIAT + D&A (+SBC) − ΔNWC; then − CapEx → UFCF. AI FCF after interest ≈ NI + D&A − CapEx − ΔNWC (D&A explicitly added). | O93: D&A IS in FCF (add-back). Charged on IS to get EBIT/NI, then added in UFCF/AI FCF so cash isn’t understated. | P93: YES — NET + for LBO. D&A IS added back in FCF: earnings (EBIT/NI) already deducted D&A, but no cash left the firm. DCF UFCF = EBIAT + D&A − ΔNWC − CapEx; AI FCF ≈ NI + D&A − CapEx − ΔNWC. Higher D&A add-back raises cash for debt sweep / IRR vs NI alone.
B94: Capex as a % of revenue | C94: 0.010652205 | D94: 0.012200737 | E94: 0.011129281 | F94: =Assumptions_Drivers!$C$24*(1-Assumptions_Drivers!$C$12) -> 0.0184 | G94: =Assumptions_Drivers!$C$24*(1-Assumptions_Drivers!$C$12) -> 0.0184 | H94: =Assumptions_Drivers!$C$24*(1-Assumptions_Drivers!$C$12) -> 0.0184 | I94: =Assumptions_Drivers!$C$24*(1-Assumptions_Drivers!$C$12) -> 0.0184 | J94: =Assumptions_Drivers!$C$24*(1-Assumptions_Drivers!$C$12) -> 0.0184 | L94: 1.84% flat every year (Drivers C24×(1−C12)). Ratio does not trend; $ CapEx rises only with +5% sales. | M94: =HYPERLINK("https://saasdb.app/learn/financials/fcf-margin/","REASONABLE: 2% midpoint × (1−8% AI cut) = 1.84% of sales") -> REASONABLE: 2% midpoint × (1−8% AI cut) = 1.84% of sales | N94: Ctrl+F: CapEx of 1–3% of revenue EQ: Assumptions_Drivers!C24=2%; C12=8%; net=1.84%. LBO F94:J94=C24*(1-C12). | O94: 1.84% is the CapEx intensity Driver. Fixing it removed BMC ~1.1% / $26–31m errors. | P94: YES — NET − for LBO. 1.84% CapEx intensity sets the cash drag on FCF/DCF.
B95: Depreciation as a % of capex | C95: 1.7772727 | D95: 1.4264151 | E95: 1.5795918 | F95: =IF(F92=0,0,ABS(F93)/F92) -> 3.8356326 | G95: =IF(G92=0,0,ABS(G93)/G92) -> 3.8356326 | H95: =IF(H92=0,0,ABS(H93)/H92) -> 3.8356326 | I95: =IF(I92=0,0,ABS(I93)/I92) -> 3.8356326 | J95: =IF(J92=0,0,ABS(J93)/J92) -> 3.8356326 | L95: n/a — diagnostic |D&A|÷CapEx each year (formula). Not a Driver; does not set cash. | M95: =HYPERLINK("https://saasdb.app/learn/financials/fcf-margin/","CAUTION — diagnostic ratio only; not a yellow Driver") -> CAUTION — diagnostic ratio only; not a yellow Driver | N95: EQ: F95=ABS(F93)/F92. No Assumptions_Drivers cell. Watch if >>1 (depreciating faster than reinvesting). | O95: Ratio is a check, not an input. Does not by itself change LBO IRR. | P95: NO — n/a sign. Diagnostic only.
B97: Software development costs | D97: 244.7 | E97: 271.4 | F97: =E97 -> 271.4 | G97: =E97 -> 271.4 | H97: =E97 -> 271.4 | I97: =E97 -> 271.4 | J97: =E97 -> 271.4 | L97: 0% new spend. Capitalized software EOP held flat at FY24. Cash CapEx already in 1.84% Drivers bucket. | M97: =HYPERLINK("https://saasdb.app/learn/financials/fcf-margin/","CAUTION — capitalized software not separately modeled; CapEx in C24") -> CAUTION — capitalized software not separately modeled; CapEx in C24 | N97: Ctrl+F: Capitalized software development costs also affect this analysis EQ: F98:J98=0; F97=E97 flat. Avoids double-counting vs Drivers CapEx. | O97: Separate software buys were BMC (~$115m+) and overstated investing cash use vs DCF $0. | P97: NO — n/a sign. Zeroed; would double-count CapEx if kept.
B98: Purchases | C98: 115.8 | D98: 132.5 | E98: 129.6 | F98: 0 | G98: 0 | H98: 0 | I98: 0 | J98: 0 | L98: 0$/yr. Purchases set to $0 (was BMC $114–135m). Matches DCF intangible/software policy. | M98: =HYPERLINK("https://saasdb.app/learn/financials/fcf-margin/","FIXED inaccuracy: BMC software purchases wiped; CapEx is Drivers 1.84%") -> FIXED inaccuracy: BMC software purchases wiped; CapEx is Drivers 1.84% | N98: EQ: F98:J98=0. Prior LBO CF subtracted ~$190m+/yr of software+intangibles — inconsistent with DCF row 26=0 and AI CapEx. | O98: Zeroing stops fake ~$200m investing outflow that crushed LBO cash vs the DCF. | P98: YES — NET + for LBO (fix). Removing false ~$115m+ software buys stops a fake cash drain.
B99: Amortization | C99: -75.7 | D99: -93.6 | E99: -108.5 | F99: 0 | G99: 0 | H99: 0 | I99: 0 | J99: 0
B100: Purchases as % of revenue | C100: 0.056069336 | D100: 0.061003683 | E100: 0.058871627 | F100: 0 | G100: 0 | H100: 0 | I100: 0 | J100: 0
B101: Amortization as a % of purchases | C101: 0.6537133 | D101: 0.70641509 | E101: 0.83719136 | F101: 0 | G101: 0 | H101: 0 | I101: 0 | J101: 0
B103: Intangible assets | D103: 257.5 | E103: 189.8 | F103: =E103 -> 189.8 | G103: =E103 -> 189.8 | H103: =E103 -> 189.8 | I103: =E103 -> 189.8 | J103: =E103 -> 189.8 | L103: 0% growth. Intangible EOP held flat; no new M&A intangibles in forecast. | M103: =HYPERLINK("https://www.sec.gov/Archives/edgar/data/1794515/000179451525000045/zi-20241231.htm","CAUTION — hold flat; no forecast M&A") -> CAUTION — hold flat; no forecast M&A | N103: EQ: F103=E103; F104=0; F105=0. DCF “Purchases of intangible assets” = 0. | O103: No modeled bolt-on M&A. Flat intangibles avoid fake amortization cash stories. | P103: NO — n/a sign. Flat BS; not in AI FCF.
B104: Purchases | C104: 0 | D104: 0 | E104: 0 | F104: 0 | G104: 0 | H104: 0 | I104: 0 | J104: 0 | L104: 0$/yr. Intangible purchases $0 (was BMC $57–85m). Aligned with DCF. | M104: =HYPERLINK("https://saasdb.app/learn/financials/fcf-margin/","FIXED: intangible purchases → $0 to match DCF!D26:H26") -> FIXED: intangible purchases → $0 to match DCF!D26:H26 | N104: EQ: F104:J104=0. DCF already had 0; LBO investing CF now matches. | O104: Removes bogus purchase cash use so LBO investing CF matches DCF UFCF CapEx-only. | P104: YES — NET + for LBO (fix). Zeroing BMC intangible buys removes false Uses of cash.
B105: Amortization | C105: -79.1 | D105: -97.7 | E105: -86.9 | F105: 0 | G105: 0 | H105: 0 | I105: 0 | J105: 0
B107: Goodwill and other assets | D107: 1940.3 | E107: 1935.2 | F107: =E107 -> 1935.2 | G107: =E107 -> 1935.2 | H107: =E107 -> 1935.2 | I107: =E107 -> 1935.2 | J107: =E107 -> 1935.2 | L107: 0% growth. Goodwill held flat — no impairment, no new deals in model. | M107: =HYPERLINK("https://www.sec.gov/Archives/edgar/data/1794515/000179451525000045/zi-20241231.htm","CAUTION — flat goodwill; non-cash for FCF") -> CAUTION — flat goodwill; non-cash for FCF | N107: EQ: F107:J107=E107. Goodwill does not enter AI_Operating FCF or DCF UFCF. | O107: Goodwill is BS-only here. LBO IRR is cash/debt-driven, not goodwill-driven. | P107: NO — n/a sign. Non-cash; no FCF/debt-sweep impact.
B109: Other liabilities | D109: 232.4 | E109: 252 | F109: 252 | G109: 252 | H109: 252 | I109: 252 | J109: 252
B111: CASH FLOW STATEMENT
...

Sheet DCF
B2: Discounted Cash Flow Model for ZoomInfo (GTM)
B3: Point of this DCF: present-value check of GTM stand-alone worth vs the LBO offer. Discount AI_Operating unlevered FCF + terminal value at WACC → EV → equity → $/share; compare to LBO!H20.
B4: Yes — rows PV of UFCF / PV of TV / Enterprise value are present values. Not a hold-to-exit LBO IRR; that lives on Strategy_Summary / Debt_Sweep_AI.
B5: General assumptions
B6: Share price as of last close | C6: =LBO!D8 -> 4.05 | K6: 4.05 | L6: cached
B7: Latest closing share price date | C7: =LBO!D9 -> 45884
B8: Diluted shares outstanding (mm) | C8: =Shares!E14 -> 307.294 | K8: 307.294
B9: Weighted average cost of capital | C9: =C59 -> 0.09295868 | K9: 0.092901527
B11: Free cash flow buildup
B12: Fiscal year | C12: 2024 | D12: 2025 | E12: 2026 | F12: 2027 | G12: 2028 | H12: 2029
B13: Fiscal year end date | C13: 45657 | D13: 46022 | E13: 46387 | F13: 46752 | G13: 47118 | H13: 47483
B15: EBITDA | C15: =AI_Operating!C13 -> 183.1 | D15: =AI_Operating!D13 -> 220.5423 | E15: =AI_Operating!E13 -> 242.98128 | F15: =AI_Operating!F13 -> 266.74594 | G15: =AI_Operating!G13 -> 291.90664 | H15: =AI_Operating!H13 -> 318.53735
B16: EBIT | C16: =AI_Operating!C16 -> 97.4 | D16: =AI_Operating!D16 -> 130.5573 | E16: =AI_Operating!E16 -> 148.49703 | F16: =AI_Operating!F16 -> 167.53747 | G16: =AI_Operating!G16 -> 187.73776 | H16: =AI_Operating!H16 -> 209.16002
B17: Tax rate | C17: =Assumptions_Drivers!$C$19 -> 0.21 | D17: =Assumptions_Drivers!$C$19 -> 0.21 | E17: =Assumptions_Drivers!$C$19 -> 0.21 | F17: =Assumptions_Drivers!$C$19 -> 0.21 | G17: =Assumptions_Drivers!$C$19 -> 0.21 | H17: =Assumptions_Drivers!$C$19 -> 0.21
B18: EBIAT (NOPAT) | C18: =C16*(1-C17) -> 76.946 | D18: =D16*(1-D17) -> 103.14027 | E18: =E16*(1-E17) -> 117.31265 | F18: =F16*(1-F17) -> 132.3546 | G18: =G16*(1-G17) -> 148.31283 | H18: =H16*(1-H17) -> 165.23642
B20: Depreciation and amortization | D20: =AI_Operating!D15 -> 89.985 | E20: =AI_Operating!E15 -> 94.48425 | F20: =AI_Operating!F15 -> 99.208463 | G20: =AI_Operating!G15 -> 104.16889 | H20: =AI_Operating!H15 -> 109.37733 | K20: D&A IS in UFCF: Unlevered CFO = EBIAT + D&A + SBC − ΔNWC (row 24).
B21: Stock based compensation (add-back) | D21: 0 | E21: 0 | F21: 0 | G21: 0 | H21: 0 | K21: POLICY: add-back = $0 (SBC treated as real cost). Assumption lives at Assumptions_Drivers!C29=14.1% and drives LBO!F60/F70 only — changing C29 does NOT change DCF UFCF unless this row is switched on. | L21: =Assumptions_Drivers!$C$29 -> 0.141 | M21: Drivers SBC % (memo only — not in UFCF)
B22: Changes in net working capital | D22: =AI_Operating!D20 -> -14.857215 | E22: =AI_Operating!E20 -> -15.600076 | F22: =AI_Operating!F20 -> -16.38008 | G22: =AI_Operating!G20 -> -17.199084 | H22: =AI_Operating!H20 -> -18.059038
B23: Other assets & liabilities | D23: 0 | E23: 0 | F23: 0 | G23: 0 | H23: 0
B24: Unlevered CFO | D24: =D18+D20+D21-D22+D23 -> 207.98248 | E24: =E18+E20+E21-E22+E23 -> 227.39698 | F24: =F18+F20+F21-F22+F23 -> 247.94315 | G24: =G18+G20+G21-G22+G23 -> 269.6808 | H24: =H18+H20+H21-H22+H23 -> 292.67278
B25: Less: Capital expenditures | D25: =-AI_Operating!D19 -> -23.460276 | E25: =-AI_Operating!E19 -> -24.63329 | F25: =-AI_Operating!F19 -> -25.864954 | G25: =-AI_Operating!G19 -> -27.158202 | H25: =-AI_Operating!H19 -> -28.516112 | K25: CapEx = AI_Operating (Drivers C24=2% × (1−C12=8%) = 1.84% of sales). Intangible purchases = $0 (row 26).
B26: Less: Purchases of intangible assets | D26: 0 | E26: 0 | F26: 0 | G26: 0 | H26: 0
B27: Unlevered FCF | D27: =D24+D25+D26 -> 184.52221 | E27: =E24+E25+E26 -> 202.76369 | F27: =F24+F25+F26 -> 222.07819 | G27: =G24+G25+G26 -> 242.52259 | H27: =H24+H25+H26 -> 264.15667
B28: % growth | E28: =IF(D27=0,0,E27/D27-1) -> 0.09885791 | F28: =IF(E27=0,0,F27/E27-1) -> 0.095256239 | G28: =IF(F27=0,0,G27/F27-1) -> 0.09205948 | H28: =IF(G27=0,0,H27/G27-1) -> 0.089204381
B30: Discount period (years, mid-year) | D30: 0.5 | E30: 1.5 | F30: 2.5 | G30: 3.5 | H30: 4.5
B31: Assume cash flows are generated at: | C31: Middle of period
B32: Midperiod adjustment factor | C32: =(1+$C$9)^0.5 -> 1.0454466
B33: Present value of Unlevered FCF | D33: =D27/(1+$C$9)^D30 -> 176.50084 | E33: =E27/(1+$C$9)^E30 -> 177.4535 | F33: =F27/(1+$C$9)^F30 -> 177.82653 | G33: =G27/(1+$C$9)^G30 -> 177.68023 | H33: =H27/(1+$C$9)^H30 -> 177.0699
B35: Perpetuity approach | E35: Exit EBITDA multiple approach
B36: Normalized FCFt+1 | C36: =H27*(1+C37) -> 269.43981 | E36: Terminal year EBITDA | H36: =H15 -> 318.53735
B37: Long term growth rate (g) | C37: =Assumptions_Drivers!C10 -> 0.02 | E37: Terminal value EBITDA multiple | H37: =Assumptions_Drivers!C20 -> 12.9
B38: Terminal value | C38: =IF(($C$9-C37)<=0,"NM",C36/($C$9-C37)) -> 3693.0466 | E38: Terminal value | H38: =H36*H37 -> 4109.1318
B39: Present value of terminal value | C39: =IF(ISNUMBER(C38),C38/(1+$C$9)^H30,0) -> 2475.5286 | E39: Present value of terminal value | H39: =H38/(1+$C$9)^H30 -> 2754.4394
B40: Present value of stage 1 cash flows | C40: =SUM(D33:H33) -> 886.53099 | E40: Present value of stage 1 cash flows | H40: =C40 -> 886.53099
B41: Enterprise value | C41: =C39+C40 -> 3362.0596 | E41: Enterprise value | H41: =H39+H40 -> 3640.9704 | K41: 3641.7347
B42: Implied TV exit EBITDA multiple | C42: =IF(H15=0,0,C38/H15) -> 11.593763 | E42: Implied TV perpetual growth rate | H42: =IF(H38=0,0,($C$9*H38-H27)/(H38+H27)) -> 0.026941465
B44: Net Debt | E44: Fair value per share
B45: Cash & equivalents (LBO latest) | C45: =LBO!D15 -> 179.9 | H45: LBO Offer | I45: Perpetuity | J45: EBITDA exit
B46: Gross debt (LBO latest filing) | C46: =ABS(LBO!D14) -> 1329.9 | E46: Enterprise value | H46: =H48+C47 -> 2705.6759 | I46: =C41 -> 3362.0596 | J46: =H41 -> 3640.9704
B47: Net debt | C47: =C46-C45 -> 1150 | E47: Less: Net debt | H47: =-C47 -> -1150 | I47: =-C47 -> -1150 | J47: =-C47 -> -1150
E48: Equity value | H48: =LBO!H20*$C$8 -> 1555.6759 | I48: =I46+I47 -> 2212.0596 | J48: =J46+J47 -> 2490.9704
B49: Cost of capital assumptions | E49: Diluted shares | H49: =$C$8 -> 307.294 | I49: =$C$8 -> 307.294 | J49: =$C$8 -> 307.294
B50: Cost of debt (wtd TLA/TLB/Notes) | C50: =(Debt_Sweep_AI!G12*Assumptions_Drivers!C27+Debt_Sweep_AI!G13*Assumptions_Drivers!C28+Debt_Sweep_AI!G14*(Assumptions_Drivers!C14+0.035))/Debt_Sweep_AI!G15 -> 0.085 | E50: Equity value per share | H50: =LBO!H20 -> 5.0625 | I50: =IF(I49=0,0,I48/I49) -> 7.198512 | J50: =IF(J49=0,0,J48/J49) -> 8.1061473 | K50: 8.1086343 | L50: cached exit $/sh
B51: Tax rate | C51: =Assumptions_Drivers!C19 -> 0.21 | E51: Premium (discount) to LBO offer | H51: NM | I51: =IF(H50=0,0,I50/H50-1) -> 0.4219283 | J51: =IF(H50=0,0,J50/H50-1) -> 0.60121429
B52: Debt (new LBO stack $m) | C52: =Debt_Sweep_AI!G15 -> 915.5
B53: Debt as a % of total capital | C53: =C52/(C52+C54) -> 0.32702268
B54: Sponsor equity check ($m) | C54: =Strategy_Summary!C20 -> 1884
B55: Risk free rate (SOFR from Drivers) | C55: =Assumptions_Drivers!C14 -> 0.043
B56: Beta (MODEL CONST — SaaS mid) | C56: 1.25
B57: Market risk premium | C57: 0.05
B58: Equity as % of total capital structure | C58: =1-C53 -> 0.67297732
B59: Cost of capital (WACC) | C59: =C58*(C55+C56*C57)+C53*C50*(1-C51) -> 0.09295868
B93: Football field (chart removed so Excel can open this file)
C114: Low | D114: Diff. | E114: High
B115: DCF exit-multiple value / share (cached) | C115: 8.1086343 | D115: 0 | E115: 8.1086343
B116: DCF perpetuity value / share (cached) | C116: 7.2071026 | D116: 0 | E116: 7.2071026
B117: LBO Offer price / share | C117: =LBO!H20 -> 5.0625 | D117: 0 | E117: =LBO!H20 -> 5.0625
B118: 52 Week Market High/Low (GTM from 52wkHL) | C118: ='52wkHL'!E5 -> 2.54 | D118: =E118-C118 -> 9.97 | E118: ='52wkHL'!E4 -> 12.51

Sheet Shares
B2: Diluted shares for ZoomInfo (GTM)
B3: $ mm except per share / share counts in millions
B5: Offer price (LBO) | E5: =LBO!H20 -> 5.0625 | F5: 5.0625 | G5: cached (formulas in E)
B6: Latest close (LBO) | E6: =LBO!D8 -> 4.05 | F6: 4.05
B7: Diluted shares outstanding (mm) | E7: =LBO!H18 -> 307.294 | F7: 307.294
B8: In-the-money exercisable options (mm) | E8: 0
B9: Total proceeds ($mm) | E9: 0
B10: Total shares repurchased (mm) | E10: 0
B11: Net dilutive options | E11: 0
B12: Dilutive impact of other securities | E12: 0
B14: Net diluted shares outstanding (mm) | E14: =E7+E11+E12 -> 307.294 | F14: 307.294
B16: Options note
B17: LBO!H18 stores diluted shares for offer value/share. No GTM option lattice — options left at 0.

Sheet 52wkHL
A1: GTM ONLY — prices are ~$2.54–$12.51, not BMC $45s
A2: 52 week high/low — ZoomInfo Technologies (ticker GTM)
A4: 52 week high | E4: 12.51
A5: 52 week low | E5: 2.54
A6: GTM daily OHLC (Yahoo 1y). Last close 4.05 matches LBO!D8. Not BMC.
A7: Date | B7: Open | C7: High | D7: Low | E7: Close | F7: Volume
A8: 46248.562 | B8: 4.25 | C8: 4.311 | D8: 4.035 | E8: 4.05 | F8: 6927400
A9: 46247.562 | B9: 3.86 | C9: 4.365 | D9: 3.811 | E9: 4.31 | F9: 9261000
A10: 46246.562 | B10: 4.05 | C10: 4.05 | D10: 3.75 | E10: 3.86 | F10: 7183300
A11: 46245.562 | B11: 4.21 | C11: 4.3 | D11: 4.055 | E11: 4.08 | F11: 6651100
A12: 46244.562 | B12: 4.13 | C12: 4.326 | D12: 4.13 | E12: 4.23 | F12: 9212600
A13: 46241.562 | B13: 4.33 | C13: 4.33 | D13: 4.05 | E13: 4.18 | F13: 11372700
A14: 46240.562 | B14: 3.78 | C14: 4.24 | D14: 3.76 | E14: 4.14 | F14: 16764400
A15: 46239.562 | B15: 3.67 | C15: 3.8 | D15: 3.595 | E15: 3.66 | F15: 11351500
A16: 46238.562 | B16: 3.46 | C16: 3.655 | D16: 3.46 | E16: 3.62 | F16: 4514800
A17: 46237.562 | B17: 3.41 | C17: 3.64 | D17: 3.4 | E17: 3.57 | F17: 7290300
A18: 46234.562 | B18: 3.33 | C18: 3.4 | D18: 3.265 | E18: 3.3 | F18: 6511600
A19: 46233.562 | B19: 3.45 | C19: 3.45 | D19: 3.18 | E19: 3.32 | F19: 6105500
... A258: 45884.562 | B258: 10.075 | C258: 10.62 | D258: 10.075 | E258: 10.43 | F258: 4757500
