Workbook

Sheet Cover
B2: ZoomInfo (GTM/ZI) — S&M → AI SDR Margin Expansion
B3: Educational ops / LBO model from FY2025 Form 10-K. Open in Excel to recalculate.
B5: Thesis | C5: Replace outbound SDRs with AI agents; expand EBITDA margin ≥500 bps
B6: Issuer | C6: ZoomInfo Technologies Inc. (ticker GTM / legacy ZI)
B7: CIK | C7: 0001794515
B8: Source 10-K | C8: https://www.sec.gov/Archives/edgar/data/1794515/000179451526000012/zi-20251231.htm
B9: Filed | C9: 2026-02-12 (FY ended 2025-12-31)
B10: Companyfacts | C10: https://data.sec.gov/api/xbrl/companyfacts/CIK0001794515.json
B12: Sheets
B13: 01_10K_Source — SEC XBRL + human capital extract
B14: 02_SM_Isolation — S&M bloat vs target % of revenue
B15: 03_Headcount_AI — SDR reduction schedule + AI agent ramp
B16: 04_EBITDA_Bridge — margin expansion to 500+ bps
B17: 05_Sensitivity — SDR cut % × AI cost → bps grid
B19: Disclaimer | C19: SDR % of S&M and AI unit costs are yellow assumptions. Illustrative — not investment advice.

Sheet 01_10K_Source
B2: FY2025 10-K source financials ($ millions unless noted)
B4: Line item | C4: FY2023 | D4: FY2024 | E4: FY2025 | F4: XBRL / note
B5: Revenue | C5: 1239.5 | D5: 1214.3 | E5: 1249.5 | F5: RevenueFromContractWithCustomerExcludingAssessedTax
B6: Selling & Marketing | C6: 408.5 | D6: 414.1 | E6: 414.6 | F6: SellingAndMarketingExpense
B7: Research & Development | C7: 191.5 | D7: 196.1 | E7: 182 | F7: ResearchAndDevelopmentExpense
B8: General & Administrative | C8: 179.6 | D8: 295.3 | E8: 206.7 | F8: GeneralAndAdministrativeExpense
B9: Operating expenses (ex-COGS) | E9: 824.2 | F9: OperatingExpenses
B10: Operating income | C10: 259.5 | D10: 97.4 | E10: 225.7 | F10: OperatingIncomeLoss
B11: Depreciation | C11: 19.6 | D11: 25.9 | E11: 30.3 | F11: Depreciation
B12: Amort. of intangibles | C12: 61 | D12: 59.8 | E12: 58.5 | F12: AmortizationOfIntangibleAssets
B13: Total D&A (dep+intang) | C13: 80.6 | D13: 85.7 | E13: 88.8 | F13: OtherDepreciationAndAmortization
B14: Share-based compensation | C14: 167.6 | D14: 138 | E14: 116.2 | F14: ShareBasedCompensation
B15: Advertising expense | E15: 37.3 | F15: AdvertisingExpense
B16: Amort. deferred commissions | C16: 75.3 | D16: 67.6 | E16: 90.2 | F16: AmortizationOfDeferredSalesCommissions
B17: Net income | C17: 107.3 | D17: 29.1 | E17: 124.2 | F17: NetIncomeLoss
B19: Implied COGS (Rev − OpEx − OpInc) | E19: =E5-E9-E10
B20: GAAP EBITDA proxy (OpInc + D&A) | E20: =E10+E13
B21: GAAP EBITDA margin | E21: =E20/E5
B22: Adj. EBITDA proxy (+SBC) | E22: =E20+E14
B23: Adj. EBITDA margin | E23: =E22/E5
B25: HUMAN CAPITAL (10-K Item 1)
B26: Total employees (12/31/2025) | E26: 3180
B27: Cost of service employees | E27: 662
B28: Sales & Marketing employees | E28: 1370
B29: R&D employees | E29: 763
B30: G&A employees | E30: 385
B31: Headcount check (sum) | E31: =E27+E28+E29+E30
B32: S&M $ / S&M employee ($000s) | E32: =E6*1000/E28
B33: S&M % of revenue | E33: =E6/E5
B35: Quote — Human Capital
B36: As of December 31, 2025, we had 3,180 employees, consisting of 662 in cost of service, 1,370 in sales and marketing, 763 in research and development, and 385 in general and administrative.

Sheet 02_SM_Isolation
B2: Isolate bloated Sales & Marketing
B4: FY2025 Revenue ($m) | C4: ='01_10K_Source'!E5
B5: FY2025 S&M ($m) | C5: ='01_10K_Source'!E6
B6: S&M % revenue | C6: =C5/C4
B8: S&M STACK (FY2025)
B9: Advertising | C9: ='01_10K_Source'!E15
B10: Deferred commission amortization | C10: ='01_10K_Source'!E16
B11: Residual S&M (people + other) | C11: =C5-C9-C10
B12: Residual as % of S&M | C12: =C11/C5
B13: Residual $ / S&M employee ($000s) | C13: =C11*1000/'01_10K_Source'!E28
B15: BENCHMARK / THESIS INPUTS (edit yellow)
B16: Target mature SaaS S&M % rev | C16: 0.22
B17: S&M bloat vs target ($m) | C17: =MAX(0,C5-C4*C16)
B18: Bloat as % of revenue | C18: =C17/C4
B19: Bloat in basis points | C19: =C18*10000
B21: 10-K: 1,370 S&M employees; S&M is ~33% of revenue. Model treats outbound SDR/BDR capacity as the AI-replaceable slice (yellow % on next sheet).

Sheet 03_Headcount_AI
B2: Headcount reduction: outbound SDRs → AI agents
B4: BASELINE
B5: S&M employees (10-K) | C5: ='01_10K_Source'!E28
B6: % of S&M that are outbound SDR/BDR | C6: 0.4
B7: Outbound SDR headcount (Y0) | C7: =ROUND(C5*C6,0)
B8: Fully loaded cost / SDR / yr ($000s) | C8: 155
B9: Addressable SDR cost pool ($m) | C9: =C7*C8/1000
B11: AI AGENT UNIT ECONOMICS
B12: AI agent seats per SDR replaced | C12: 1
B13: AI platform + compute / seat / yr ($000s) | C13: 15
B14: Human oversight FTE per 20 AI seats | C14: 1
B15: Oversight fully loaded / FTE / yr ($000s) | C15: 150
B16: One-time severance / SDR ($000s) | C16: 25
B17: One-time AI build / integration ($m) in Y1 | C17: 8
B19: REDUCTION SCHEDULE (% of Y0 SDRs exited by year-end)
B20: Year | C20: 2026 | D20: 2027 | E20: 2028
B21: Cumulative % SDRs replaced | C21: 0.45 | D21: 0.8 | E21: 0.95
B22: SDRs remaining | C22: =ROUND($C$7*(1-C21),0) | D22: =ROUND($C$7*(1-D21),0) | E22: =ROUND($C$7*(1-E21),0)
B23: SDRs exited (cumulative) | C23: =$C$7-C22 | D23: =$C$7-D22 | E23: =$C$7-E22
B24: SDRs exited this year | C24: =C23 | D24: =D23-C23 | E24: =E23-D23
B25: Avg SDRs during year | C25: =($C$7+C22)/2 | D25: =(C22+D22)/2 | E25: =(D22+E22)/2
B27: AI SEATS & OVERSIGHT
B28: AI seats (cum.) | C28: =C23*$C$12 | D28: =D23*$C$12 | E28: =E23*$C$12
B29: Oversight FTEs | C29: =ROUNDUP(C28/(20/$C$14),0) | D29: =ROUNDUP(D28/(20/$C$14),0) | E29: =ROUNDUP(E28/(20/$C$14),0)
B31: P&L IMPACT ($m)
B32: SDR cash cost (avg HC × cost) | C32: =C25*$C$8/1000 | D32: =D25*$C$8/1000 | E32: =E25*$C$8/1000
B33: Baseline SDR cost if no program | C33: =$C$9 | D33: =$C$9 | E33: =$C$9
B34: Gross SDR savings vs baseline | C34: =C33-C32 | D34: =D33-D32 | E34: =E33-E32
B35: AI seat opex | C35: =C28*$C$13/1000 | D35: =D28*$C$13/1000 | E35: =E28*$C$13/1000
B36: Oversight opex | C36: =C29*$C$15/1000 | D36: =D29*$C$15/1000 | E36: =E29*$C$15/1000
B37: Severance (this year's exits) | C37: =C24*$C$16/1000 | D37: =D24*$C$16/1000 | E37: =E24*$C$16/1000
B38: AI build (Y1 only) | C38: =$C$17 | D38: 0 | E38: 0
B39: Net EBITDA benefit (in-year, after one-time) | C39: =C34-C35-C36-C37-C38 | D39: =D34-D35-D36-D37-D38 | E39: =E34-E35-E36-E37-E38
B40: Year-end run-rate benefit (ex one-time) | C40: =(C23*$C$8/1000)-(C28*$C$13/1000)-(C29*$C$15/1000) | D40: =(D23*$C$8/1000)-(D28*$C$13/1000)-(D29*$C$15/1000) | E40: =(E23*$C$8/1000)-(E28*$C$13/1000)-(E29*$C$15/1000)

Sheet 04_EBITDA_Bridge
B2: EBITDA margin expansion bridge (target ≥500 bps)
B4: FY2025 baseline Revenue ($m) | C4: ='01_10K_Source'!E5
B5: FY2025 GAAP EBITDA proxy ($m) | C5: ='01_10K_Source'!E20
B6: Baseline EBITDA margin | C6: =C5/C4
B7: Target margin expansion (bps) | C7: 500
B8: Required incremental EBITDA ($m) | C8: =C4*C7/10000
B10: Year | C10: 2026 | D10: 2027 | E10: 2028
B11: Revenue (flat case for margin math) | C11: =$C$4 | D11: =$C$4 | E11: =$C$4
B12: Net EBITDA benefit from program | C12: ='03_Headcount_AI'!C39 | D12: ='03_Headcount_AI'!D39 | E12: ='03_Headcount_AI'!E39
B13: Run-rate benefit (ex one-time) | C13: ='03_Headcount_AI'!C40 | D13: ='03_Headcount_AI'!D40 | E13: ='03_Headcount_AI'!E40
B14: Pro forma EBITDA | C14: =$C$5+C12 | D14: =$C$5+D12 | E14: =$C$5+E12
B15: Pro forma EBITDA margin | C15: =C14/C11 | D15: =D14/D11 | E15: =E14/E11
B16: Margin expansion (bps) | C16: =(C15-$C$6)*10000 | D16: =(D15-$C$6)*10000 | E16: =(E15-$C$6)*10000
B17: Run-rate expansion (bps) | C17: =(C13/$C$4)*10000 | D17: =(D13/$C$4)*10000 | E17: =(E13/$C$4)*10000
B18: Hits ≥500 bps run-rate? | C18: =IF(C17>=$C$7,"YES","NO") | D18: =IF(D17>=$C$7,"YES","NO") | E18: =IF(E17>=$C$7,"YES","NO")
B20: S&M % revenue bridge
B21: Baseline S&M % | C21: ='02_SM_Isolation'!C6
B22: PF S&M $ (baseline − SDR save + AI/oversight) | C22: ='01_10K_Source'!E6-'03_Headcount_AI'!C34+'03_Headcount_AI'!C35+'03_Headcount_AI'!C36 | D22: ='01_10K_Source'!E6-'03_Headcount_AI'!D34+'03_Headcount_AI'!D35+'03_Headcount_AI'!D36 | E22: ='01_10K_Source'!E6-'03_Headcount_AI'!E34+'03_Headcount_AI'!E35+'03_Headcount_AI'!E36
B23: PF S&M % revenue | C23: =C22/$C$4 | D23: =D22/$C$4 | E23: =E22/$C$4
B25: Yellow cells on 03_Headcount_AI drive the bridge. Base case sized to clear 500 bps by Y3 run-rate: 40% of S&M = outbound SDRs; 95% replaced; $155k/SDR vs $15k AI seat + oversight. 500 bps on $1,249.5m revenue needs ~$62.5m run-rate EBITDA.

Sheet 05_Sensitivity
B2: Sensitivity — Y3 run-rate margin expansion (bps)
B3: Rows = cumulative % SDRs replaced; Cols = AI $/seat-yr ($000s). Other inputs from 03_Headcount_AI.
B5: SDR0 | C5: ='03_Headcount_AI'!C7
B6: SDR cost $k | C6: ='03_Headcount_AI'!C8
B7: Seats/SDR | C7: ='03_Headcount_AI'!C12
B8: Oversight $k | C8: ='03_Headcount_AI'!C15
B9: Revenue $m | C9: ='01_10K_Source'!E5
B11: bps \ AI $k | C11: 8 | D11: 12 | E11: 18 | F11: 24 | G11: 30 | H11: 40
B12: 0.5 | C12: =(($C$5*0.5)*$C$6/1000-($C$5*0.5)*$C$7*8/1000-ROUNDUP(($C$5*0.5)*$C$7/20,0)*$C$8/1000)/$C$9*10000 | D12: =(($C$5*0.5)*$C$6/1000-($C$5*0.5)*$C$7*12/1000-ROUNDUP(($C$5*0.5)*$C$7/20,0)*$C$8/1000)/$C$9*10000 | E12: =(($C$5*0.5)*$C$6/1000-($C$5*0.5)*$C$7*18/1000-ROUNDUP(($C$5*0.5)*$C$7/20,0)*$C$8/1000)/$C$9*10000 | F12: =(($C$5*0.5)*$C$6/1000-($C$5*0.5)*$C$7*24/1000-ROUNDUP(($C$5*0.5)*$C$7/20,0)*$C$8/1000)/$C$9*10000 | G12: =(($C$5*0.5)*$C$6/1000-($C$5*0.5)*$C$7*30/1000-ROUNDUP(($C$5*0.5)*$C$7/20,0)*$C$8/1000)/$C$9*10000 | H12: =(($C$5*0.5)*$C$6/1000-($C$5*0.5)*$C$7*40/1000-ROUNDUP(($C$5*0.5)*$C$7/20,0)*$C$8/1000)/$C$9*10000
B13: 0.6 | C13: =(($C$5*0.6)*$C$6/1000-($C$5*0.6)*$C$7*8/1000-ROUNDUP(($C$5*0.6)*$C$7/20,0)*$C$8/1000)/$C$9*10000 | D13: =(($C$5*0.6)*$C$6/1000-($C$5*0.6)*$C$7*12/1000-ROUNDUP(($C$5*0.6)*$C$7/20,0)*$C$8/1000)/$C$9*10000 | E13: =(($C$5*0.6)*$C$6/1000-($C$5*0.6)*$C$7*18/1000-ROUNDUP(($C$5*0.6)*$C$7/20,0)*$C$8/1000)/$C$9*10000 | F13: =(($C$5*0.6)*$C$6/1000-($C$5*0.6)*$C$7*24/1000-ROUNDUP(($C$5*0.6)*$C$7/20,0)*$C$8/1000)/$C$9*10000 | G13: =(($C$5*0.6)*$C$6/1000-($C$5*0.6)*$C$7*30/1000-ROUNDUP(($C$5*0.6)*$C$7/20,0)*$C$8/1000)/$C$9*10000 | H13: =(($C$5*0.6)*$C$6/1000-($C$5*0.6)*$C$7*40/1000-ROUNDUP(($C$5*0.6)*$C$7/20,0)*$C$8/1000)/$C$9*10000
B14: 0.7 | C14: =(($C$5*0.7)*$C$6/1000-($C$5*0.7)*$C$7*8/1000-ROUNDUP(($C$5*0.7)*$C$7/20,0)*$C$8/1000)/$C$9*10000 | D14: =(($C$5*0.7)*$C$6/1000-($C$5*0.7)*$C$7*12/1000-ROUNDUP(($C$5*0.7)*$C$7/20,0)*$C$8/1000)/$C$9*10000 | E14: =(($C$5*0.7)*$C$6/1000-($C$5*0.7)*$C$7*18/1000-ROUNDUP(($C$5*0.7)*$C$7/20,0)*$C$8/1000)/$C$9*10000 | F14: =(($C$5*0.7)*$C$6/1000-($C$5*0.7)*$C$7*24/1000-ROUNDUP(($C$5*0.7)*$C$7/20,0)*$C$8/1000)/$C$9*10000 | G14: =(($C$5*0.7)*$C$6/1000-($C$5*0.7)*$C$7*30/1000-ROUNDUP(($C$5*0.7)*$C$7/20,0)*$C$8/1000)/$C$9*10000 | H14: =(($C$5*0.7)*$C$6/1000-($C$5*0.7)*$C$7*40/1000-ROUNDUP(($C$5*0.7)*$C$7/20,0)*$C$8/1000)/$C$9*10000
B15: 0.8 | C15: =(($C$5*0.8)*$C$6/1000-($C$5*0.8)*$C$7*8/1000-ROUNDUP(($C$5*0.8)*$C$7/20,0)*$C$8/1000)/$C$9*10000 | D15: =(($C$5*0.8)*$C$6/1000-($C$5*0.8)*$C$7*12/1000-ROUNDUP(($C$5*0.8)*$C$7/20,0)*$C$8/1000)/$C$9*10000 | E15: =(($C$5*0.8)*$C$6/1000-($C$5*0.8)*$C$7*18/1000-ROUNDUP(($C$5*0.8)*$C$7/20,0)*$C$8/1000)/$C$9*10000 | F15: =(($C$5*0.8)*$C$6/1000-($C$5*0.8)*$C$7*24/1000-ROUNDUP(($C$5*0.8)*$C$7/20,0)*$C$8/1000)/$C$9*10000 | G15: =(($C$5*0.8)*$C$6/1000-($C$5*0.8)*$C$7*30/1000-ROUNDUP(($C$5*0.8)*$C$7/20,0)*$C$8/1000)/$C$9*10000 | H15: =(($C$5*0.8)*$C$6/1000-($C$5*0.8)*$C$7*40/1000-ROUNDUP(($C$5*0.8)*$C$7/20,0)*$C$8/1000)/$C$9*10000
B16: 0.9 | C16: =(($C$5*0.9)*$C$6/1000-($C$5*0.9)*$C$7*8/1000-ROUNDUP(($C$5*0.9)*$C$7/20,0)*$C$8/1000)/$C$9*10000 | D16: =(($C$5*0.9)*$C$6/1000-($C$5*0.9)*$C$7*12/1000-ROUNDUP(($C$5*0.9)*$C$7/20,0)*$C$8/1000)/$C$9*10000 | E16: =(($C$5*0.9)*$C$6/1000-($C$5*0.9)*$C$7*18/1000-ROUNDUP(($C$5*0.9)*$C$7/20,0)*$C$8/1000)/$C$9*10000 | F16: =(($C$5*0.9)*$C$6/1000-($C$5*0.9)*$C$7*24/1000-ROUNDUP(($C$5*0.9)*$C$7/20,0)*$C$8/1000)/$C$9*10000 | G16: =(($C$5*0.9)*$C$6/1000-($C$5*0.9)*$C$7*30/1000-ROUNDUP(($C$5*0.9)*$C$7/20,0)*$C$8/1000)/$C$9*10000 | H16: =(($C$5*0.9)*$C$6/1000-($C$5*0.9)*$C$7*40/1000-ROUNDUP(($C$5*0.9)*$C$7/20,0)*$C$8/1000)/$C$9*10000
B17: 1 | C17: =(($C$5*1.0)*$C$6/1000-($C$5*1.0)*$C$7*8/1000-ROUNDUP(($C$5*1.0)*$C$7/20,0)*$C$8/1000)/$C$9*10000 | D17: =(($C$5*1.0)*$C$6/1000-($C$5*1.0)*$C$7*12/1000-ROUNDUP(($C$5*1.0)*$C$7/20,0)*$C$8/1000)/$C$9*10000 | E17: =(($C$5*1.0)*$C$6/1000-($C$5*1.0)*$C$7*18/1000-ROUNDUP(($C$5*1.0)*$C$7/20,0)*$C$8/1000)/$C$9*10000 | F17: =(($C$5*1.0)*$C$6/1000-($C$5*1.0)*$C$7*24/1000-ROUNDUP(($C$5*1.0)*$C$7/20,0)*$C$8/1000)/$C$9*10000 | G17: =(($C$5*1.0)*$C$6/1000-($C$5*1.0)*$C$7*30/1000-ROUNDUP(($C$5*1.0)*$C$7/20,0)*$C$8/1000)/$C$9*10000 | H17: =(($C$5*1.0)*$C$6/1000-($C$5*1.0)*$C$7*40/1000-ROUNDUP(($C$5*1.0)*$C$7/20,0)*$C$8/1000)/$C$9*10000
B20: Base case Y3 run-rate bps (from bridge) | C20: ='04_EBITDA_Bridge'!E17
